Workbook

Sheet 00_Control_Panel
B2: Warby Parker - 3-Statement Model
B4: Scenario Selector | C4: Best | D4: =IF(OR(C4="Base",C4="Best",C4="Worst"),"✓ Valid","⚠ INVALID SCENARIO") -> ✓ Valid
B5: Valid scenarios: | C5: Base, Best, Worst

Sheet 01_Assumptions
A1: Assumptions - Driver Inputs
A3: Section A: Historical Ratios (FY2021-FY2025)
A5: Driver | B5: 2021 | C5: 2022 | D5: 2023 | E5: 2024 | F5: 2025
A6: revenue_growth_pct | B6: =IF(INDEX('10_Data_Sources'!$B$159:$F$171,MATCH($A6,'10_Data_Sources'!$A$159:$A$171,0),MATCH(B$5,'10_Data_Sources'!$B$158:$F$158,0))="","–",INDEX('10_Data_Sources'!$B$159:$F$171,MATCH($A6,'10_Data_Sources'!$A$159:$A$171,0),MATCH(B$5,'10_Data_Sources'!$B$158:$F$158,0))) -> – | C6: =IF(INDEX('10_Data_Sources'!$B$159:$F$171,MATCH($A6,'10_Data_Sources'!$A$159:$A$171,0),MATCH(C$5,'10_Data_Sources'!$B$158:$F$158,0))="","–",INDEX('10_Data_Sources'!$B$159:$F$171,MATCH($A6,'10_Data_Sources'!$A$159:$A$171,0),MATCH(C$5,'10_Data_Sources'!$B$158:$F$158,0))) -> 0.10598042 | D6: =IF(INDEX('10_Data_Sources'!$B$159:$F$171,MATCH($A6,'10_Data_Sources'!$A$159:$A$171,0),MATCH(D$5,'10_Data_Sources'!$B$158:$F$158,0))="","–",INDEX('10_Data_Sources'!$B$159:$F$171,MATCH($A6,'10_Data_Sources'!$A$159:$A$171,0),MATCH(D$5,'10_Data_Sources'!$B$158:$F$158,0))) -> 0.11979863 | E6: =IF(INDEX('10_Data_Sources'!$B$159:$F$171,MATCH($A6,'10_Data_Sources'!$A$159:$A$171,0),MATCH(E$5,'10_Data_Sources'!$B$158:$F$158,0))="","–",INDEX('10_Data_Sources'!$B$159:$F$171,MATCH($A6,'10_Data_Sources'!$A$159:$A$171,0),MATCH(E$5,'10_Data_Sources'!$B$158:$F$158,0))) -> 0.15162034 | F6: =IF(INDEX('10_Data_Sources'!$B$159:$F$171,MATCH($A6,'10_Data_Sources'!$A$159:$A$171,0),MATCH(F$5,'10_Data_Sources'!$B$158:$F$158,0))="","–",INDEX('10_Data_Sources'!$B$159:$F$171,MATCH($A6,'10_Data_Sources'!$A$159:$A$171,0),MATCH(F$5,'10_Data_Sources'!$B$158:$F$158,0))) -> 0.13041364
A7: gross_margin_pct | B7: =IF(INDEX('10_Data_Sources'!$B$159:$F$171,MATCH($A7,'10_Data_Sources'!$A$159:$A$171,0),MATCH(B$5,'10_Data_Sources'!$B$158:$F$158,0))="","–",INDEX('10_Data_Sources'!$B$159:$F$171,MATCH($A7,'10_Data_Sources'!$A$159:$A$171,0),MATCH(B$5,'10_Data_Sources'!$B$158:$F$158,0))) -> 0.5875558 | C7: =IF(INDEX('10_Data_Sources'!$B$159:$F$171,MATCH($A7,'10_Data_Sources'!$A$159:$A$171,0),MATCH(C$5,'10_Data_Sources'!$B$158:$F$158,0))="","–",INDEX('10_Data_Sources'!$B$159:$F$171,MATCH($A7,'10_Data_Sources'!$A$159:$A$171,0),MATCH(C$5,'10_Data_Sources'!$B$158:$F$158,0))) -> 0.57023099 | D7: =IF(INDEX('10_Data_Sources'!$B$159:$F$171,MATCH($A7,'10_Data_Sources'!$A$159:$A$171,0),MATCH(D$5,'10_Data_Sources'!$B$158:$F$158,0))="","–",INDEX('10_Data_Sources'!$B$159:$F$171,MATCH($A7,'10_Data_Sources'!$A$159:$A$171,0),MATCH(D$5,'10_Data_Sources'!$B$158:$F$158,0))) -> 0.54530171 | E7: =IF(INDEX('10_Data_Sources'!$B$159:$F$171,MATCH($A7,'10_Data_Sources'!$A$159:$A$171,0),MATCH(E$5,'10_Data_Sources'!$B$158:$F$158,0))="","–",INDEX('10_Data_Sources'!$B$159:$F$171,MATCH($A7,'10_Data_Sources'!$A$159:$A$171,0),MATCH(E$5,'10_Data_Sources'!$B$158:$F$158,0))) -> 0.5533848 | F7: =IF(INDEX('10_Data_Sources'!$B$159:$F$171,MATCH($A7,'10_Data_Sources'!$A$159:$A$171,0),MATCH(F$5,'10_Data_Sources'!$B$158:$F$158,0))="","–",INDEX('10_Data_Sources'!$B$159:$F$171,MATCH($A7,'10_Data_Sources'!$A$159:$A$171,0),MATCH(F$5,'10_Data_Sources'!$B$158:$F$158,0))) -> 0.53971362
A8: cogs_pct_revenue | B8: =IF(INDEX('10_Data_Sources'!$B$159:$F$171,MATCH($A8,'10_Data_Sources'!$A$159:$A$171,0),MATCH(B$5,'10_Data_Sources'!$B$158:$F$158,0))="","–",INDEX('10_Data_Sources'!$B$159:$F$171,MATCH($A8,'10_Data_Sources'!$A$159:$A$171,0),MATCH(B$5,'10_Data_Sources'!$B$158:$F$158,0))) -> 0.4124442 | C8: =IF(INDEX('10_Data_Sources'!$B$159:$F$171,MATCH($A8,'10_Data_Sources'!$A$159:$A$171,0),MATCH(C$5,'10_Data_Sources'!$B$158:$F$158,0))="","–",INDEX('10_Data_Sources'!$B$159:$F$171,MATCH($A8,'10_Data_Sources'!$A$159:$A$171,0),MATCH(C$5,'10_Data_Sources'!$B$158:$F$158,0))) -> 0.42976901 | D8: =IF(INDEX('10_Data_Sources'!$B$159:$F$171,MATCH($A8,'10_Data_Sources'!$A$159:$A$171,0),MATCH(D$5,'10_Data_Sources'!$B$158:$F$158,0))="","–",INDEX('10_Data_Sources'!$B$159:$F$171,MATCH($A8,'10_Data_Sources'!$A$159:$A$171,0),MATCH(D$5,'10_Data_Sources'!$B$158:$F$158,0))) -> 0.45469829 | E8: =IF(INDEX('10_Data_Sources'!$B$159:$F$171,MATCH($A8,'10_Data_Sources'!$A$159:$A$171,0),MATCH(E$5,'10_Data_Sources'!$B$158:$F$158,0))="","–",INDEX('10_Data_Sources'!$B$159:$F$171,MATCH($A8,'10_Data_Sources'!$A$159:$A$171,0),MATCH(E$5,'10_Data_Sources'!$B$158:$F$158,0))) -> 0.4466152 | F8: =IF(INDEX('10_Data_Sources'!$B$159:$F$171,MATCH($A8,'10_Data_Sources'!$A$159:$A$171,0),MATCH(F$5,'10_Data_Sources'!$B$158:$F$158,0))="","–",INDEX('10_Data_Sources'!$B$159:$F$171,MATCH($A8,'10_Data_Sources'!$A$159:$A$171,0),MATCH(F$5,'10_Data_Sources'!$B$158:$F$158,0))) -> 0.46028638
A9: sga_pct_revenue | B9: =IF(INDEX('10_Data_Sources'!$B$159:$F$171,MATCH($A9,'10_Data_Sources'!$A$159:$A$171,0),MATCH(B$5,'10_Data_Sources'!$B$158:$F$158,0))="","–",INDEX('10_Data_Sources'!$B$159:$F$171,MATCH($A9,'10_Data_Sources'!$A$159:$A$171,0),MATCH(B$5,'10_Data_Sources'!$B$158:$F$158,0))) -> 0.85320212 | C9: =IF(INDEX('10_Data_Sources'!$B$159:$F$171,MATCH($A9,'10_Data_Sources'!$A$159:$A$171,0),MATCH(C$5,'10_Data_Sources'!$B$158:$F$158,0))="","–",INDEX('10_Data_Sources'!$B$159:$F$171,MATCH($A9,'10_Data_Sources'!$A$159:$A$171,0),MATCH(C$5,'10_Data_Sources'!$B$158:$F$158,0))) -> 0.75615437 | D9: =IF(INDEX('10_Data_Sources'!$B$159:$F$171,MATCH($A9,'10_Data_Sources'!$A$159:$A$171,0),MATCH(D$5,'10_Data_Sources'!$B$158:$F$158,0))="","–",INDEX('10_Data_Sources'!$B$159:$F$171,MATCH($A9,'10_Data_Sources'!$A$159:$A$171,0),MATCH(D$5,'10_Data_Sources'!$B$158:$F$158,0))) -> 0.65279613 | E9: =IF(INDEX('10_Data_Sources'!$B$159:$F$171,MATCH($A9,'10_Data_Sources'!$A$159:$A$171,0),MATCH(E$5,'10_Data_Sources'!$B$158:$F$158,0))="","–",INDEX('10_Data_Sources'!$B$159:$F$171,MATCH($A9,'10_Data_Sources'!$A$159:$A$171,0),MATCH(E$5,'10_Data_Sources'!$B$158:$F$158,0))) -> 0.59242463 | F9: =IF(INDEX('10_Data_Sources'!$B$159:$F$171,MATCH($A9,'10_Data_Sources'!$A$159:$A$171,0),MATCH(F$5,'10_Data_Sources'!$B$158:$F$158,0))="","–",INDEX('10_Data_Sources'!$B$159:$F$171,MATCH($A9,'10_Data_Sources'!$A$159:$A$171,0),MATCH(F$5,'10_Data_Sources'!$B$158:$F$158,0))) -> 0.54583355
A10: operating_margin_pct | B10: =IF(INDEX('10_Data_Sources'!$B$159:$F$171,MATCH($A10,'10_Data_Sources'!$A$159:$A$171,0),MATCH(B$5,'10_Data_Sources'!$B$158:$F$158,0))="","–",INDEX('10_Data_Sources'!$B$159:$F$171,MATCH($A10,'10_Data_Sources'!$A$159:$A$171,0),MATCH(B$5,'10_Data_Sources'!$B$158:$F$158,0))) -> -0.26564632 | C10: =IF(INDEX('10_Data_Sources'!$B$159:$F$171,MATCH($A10,'10_Data_Sources'!$A$159:$A$171,0),MATCH(C$5,'10_Data_Sources'!$B$158:$F$158,0))="","–",INDEX('10_Data_Sources'!$B$159:$F$171,MATCH($A10,'10_Data_Sources'!$A$159:$A$171,0),MATCH(C$5,'10_Data_Sources'!$B$158:$F$158,0))) -> -0.18592337 | D10: =IF(INDEX('10_Data_Sources'!$B$159:$F$171,MATCH($A10,'10_Data_Sources'!$A$159:$A$171,0),MATCH(D$5,'10_Data_Sources'!$B$158:$F$158,0))="","–",INDEX('10_Data_Sources'!$B$159:$F$171,MATCH($A10,'10_Data_Sources'!$A$159:$A$171,0),MATCH(D$5,'10_Data_Sources'!$B$158:$F$158,0))) -> -0.10749442 | E10: =IF(INDEX('10_Data_Sources'!$B$159:$F$171,MATCH($A10,'10_Data_Sources'!$A$159:$A$171,0),MATCH(E$5,'10_Data_Sources'!$B$158:$F$158,0))="","–",INDEX('10_Data_Sources'!$B$159:$F$171,MATCH($A10,'10_Data_Sources'!$A$159:$A$171,0),MATCH(E$5,'10_Data_Sources'!$B$158:$F$158,0))) -> -0.039039822 | F10: =IF(INDEX('10_Data_Sources'!$B$159:$F$171,MATCH($A10,'10_Data_Sources'!$A$159:$A$171,0),MATCH(F$5,'10_Data_Sources'!$B$158:$F$158,0))="","–",INDEX('10_Data_Sources'!$B$159:$F$171,MATCH($A10,'10_Data_Sources'!$A$159:$A$171,0),MATCH(F$5,'10_Data_Sources'!$B$158:$F$158,0))) -> -0.0061199328
A11: net_margin_pct | B11: =IF(INDEX('10_Data_Sources'!$B$159:$F$171,MATCH($A11,'10_Data_Sources'!$A$159:$A$171,0),MATCH(B$5,'10_Data_Sources'!$B$158:$F$158,0))="","–",INDEX('10_Data_Sources'!$B$159:$F$171,MATCH($A11,'10_Data_Sources'!$A$159:$A$171,0),MATCH(B$5,'10_Data_Sources'!$B$158:$F$158,0))) -> -0.26677429 | C11: =IF(INDEX('10_Data_Sources'!$B$159:$F$171,MATCH($A11,'10_Data_Sources'!$A$159:$A$171,0),MATCH(C$5,'10_Data_Sources'!$B$158:$F$158,0))="","–",INDEX('10_Data_Sources'!$B$159:$F$171,MATCH($A11,'10_Data_Sources'!$A$159:$A$171,0),MATCH(C$5,'10_Data_Sources'!$B$158:$F$158,0))) -> -0.18456911 | D11: =IF(INDEX('10_Data_Sources'!$B$159:$F$171,MATCH($A11,'10_Data_Sources'!$A$159:$A$171,0),MATCH(D$5,'10_Data_Sources'!$B$158:$F$158,0))="","–",INDEX('10_Data_Sources'!$B$159:$F$171,MATCH($A11,'10_Data_Sources'!$A$159:$A$171,0),MATCH(D$5,'10_Data_Sources'!$B$158:$F$158,0))) -> -0.094356976 | E11: =IF(INDEX('10_Data_Sources'!$B$159:$F$171,MATCH($A11,'10_Data_Sources'!$A$159:$A$171,0),MATCH(E$5,'10_Data_Sources'!$B$158:$F$158,0))="","–",INDEX('10_Data_Sources'!$B$159:$F$171,MATCH($A11,'10_Data_Sources'!$A$159:$A$171,0),MATCH(E$5,'10_Data_Sources'!$B$158:$F$158,0))) -> -0.026435373 | F11: =IF(INDEX('10_Data_Sources'!$B$159:$F$171,MATCH($A11,'10_Data_Sources'!$A$159:$A$171,0),MATCH(F$5,'10_Data_Sources'!$B$158:$F$158,0))="","–",INDEX('10_Data_Sources'!$B$159:$F$171,MATCH($A11,'10_Data_Sources'!$A$159:$A$171,0),MATCH(F$5,'10_Data_Sources'!$B$158:$F$158,0))) -> 0.0018820858
A12: effective_tax_rate_pct | B12: =IF(INDEX('10_Data_Sources'!$B$159:$F$171,MATCH($A12,'10_Data_Sources'!$A$159:$A$171,0),MATCH(B$5,'10_Data_Sources'!$B$158:$F$158,0))="","–",INDEX('10_Data_Sources'!$B$159:$F$171,MATCH($A12,'10_Data_Sources'!$A$159:$A$171,0),MATCH(B$5,'10_Data_Sources'!$B$158:$F$158,0))) -> – | C12: =IF(INDEX('10_Data_Sources'!$B$159:$F$171,MATCH($A12,'10_Data_Sources'!$A$159:$A$171,0),MATCH(C$5,'10_Data_Sources'!$B$158:$F$158,0))="","–",INDEX('10_Data_Sources'!$B$159:$F$171,MATCH($A12,'10_Data_Sources'!$A$159:$A$171,0),MATCH(C$5,'10_Data_Sources'!$B$158:$F$158,0))) -> – | D12: =IF(INDEX('10_Data_Sources'!$B$159:$F$171,MATCH($A12,'10_Data_Sources'!$A$159:$A$171,0),MATCH(D$5,'10_Data_Sources'!$B$158:$F$158,0))="","–",INDEX('10_Data_Sources'!$B$159:$F$171,MATCH($A12,'10_Data_Sources'!$A$159:$A$171,0),MATCH(D$5,'10_Data_Sources'!$B$158:$F$158,0))) -> – | E12: =IF(INDEX('10_Data_Sources'!$B$159:$F$171,MATCH($A12,'10_Data_Sources'!$A$159:$A$171,0),MATCH(E$5,'10_Data_Sources'!$B$158:$F$158,0))="","–",INDEX('10_Data_Sources'!$B$159:$F$171,MATCH($A12,'10_Data_Sources'!$A$159:$A$171,0),MATCH(E$5,'10_Data_Sources'!$B$158:$F$158,0))) -> – | F12: =IF(INDEX('10_Data_Sources'!$B$159:$F$171,MATCH($A12,'10_Data_Sources'!$A$159:$A$171,0),MATCH(F$5,'10_Data_Sources'!$B$158:$F$158,0))="","–",INDEX('10_Data_Sources'!$B$159:$F$171,MATCH($A12,'10_Data_Sources'!$A$159:$A$171,0),MATCH(F$5,'10_Data_Sources'!$B$158:$F$158,0))) -> 0.46072954
A13: dso_days | B13: =IF(INDEX('10_Data_Sources'!$B$159:$F$171,MATCH($A13,'10_Data_Sources'!$A$159:$A$171,0),MATCH(B$5,'10_Data_Sources'!$B$158:$F$158,0))="","–",INDEX('10_Data_Sources'!$B$159:$F$171,MATCH($A13,'10_Data_Sources'!$A$159:$A$171,0),MATCH(B$5,'10_Data_Sources'!$B$158:$F$158,0))) -> 0.6695291 | C13: =IF(INDEX('10_Data_Sources'!$B$159:$F$171,MATCH($A13,'10_Data_Sources'!$A$159:$A$171,0),MATCH(C$5,'10_Data_Sources'!$B$158:$F$158,0))="","–",INDEX('10_Data_Sources'!$B$159:$F$171,MATCH($A13,'10_Data_Sources'!$A$159:$A$171,0),MATCH(C$5,'10_Data_Sources'!$B$158:$F$158,0))) -> 0.87571391 | D13: =IF(INDEX('10_Data_Sources'!$B$159:$F$171,MATCH($A13,'10_Data_Sources'!$A$159:$A$171,0),MATCH(D$5,'10_Data_Sources'!$B$158:$F$158,0))="","–",INDEX('10_Data_Sources'!$B$159:$F$171,MATCH($A13,'10_Data_Sources'!$A$159:$A$171,0),MATCH(D$5,'10_Data_Sources'!$B$158:$F$158,0))) -> 0.96949676 | E13: =IF(INDEX('10_Data_Sources'!$B$159:$F$171,MATCH($A13,'10_Data_Sources'!$A$159:$A$171,0),MATCH(E$5,'10_Data_Sources'!$B$158:$F$158,0))="","–",INDEX('10_Data_Sources'!$B$159:$F$171,MATCH($A13,'10_Data_Sources'!$A$159:$A$171,0),MATCH(E$5,'10_Data_Sources'!$B$158:$F$158,0))) -> 0.92182831 | F13: =IF(INDEX('10_Data_Sources'!$B$159:$F$171,MATCH($A13,'10_Data_Sources'!$A$159:$A$171,0),MATCH(F$5,'10_Data_Sources'!$B$158:$F$158,0))="","–",INDEX('10_Data_Sources'!$B$159:$F$171,MATCH($A13,'10_Data_Sources'!$A$159:$A$171,0),MATCH(F$5,'10_Data_Sources'!$B$158:$F$158,0))) -> 1.3751785
A14: dio_days | B14: =IF(INDEX('10_Data_Sources'!$B$159:$F$171,MATCH($A14,'10_Data_Sources'!$A$159:$A$171,0),MATCH(B$5,'10_Data_Sources'!$B$158:$F$158,0))="","–",INDEX('10_Data_Sources'!$B$159:$F$171,MATCH($A14,'10_Data_Sources'!$A$159:$A$171,0),MATCH(B$5,'10_Data_Sources'!$B$158:$F$158,0))) -> 93.430928 | C14: =IF(INDEX('10_Data_Sources'!$B$159:$F$171,MATCH($A14,'10_Data_Sources'!$A$159:$A$171,0),MATCH(C$5,'10_Data_Sources'!$B$158:$F$158,0))="","–",INDEX('10_Data_Sources'!$B$159:$F$171,MATCH($A14,'10_Data_Sources'!$A$159:$A$171,0),MATCH(C$5,'10_Data_Sources'!$B$158:$F$158,0))) -> 97.761214 | D14: =IF(INDEX('10_Data_Sources'!$B$159:$F$171,MATCH($A14,'10_Data_Sources'!$A$159:$A$171,0),MATCH(D$5,'10_Data_Sources'!$B$158:$F$158,0))="","–",INDEX('10_Data_Sources'!$B$159:$F$171,MATCH($A14,'10_Data_Sources'!$A$159:$A$171,0),MATCH(D$5,'10_Data_Sources'!$B$158:$F$158,0))) -> 74.589004 | E14: =IF(INDEX('10_Data_Sources'!$B$159:$F$171,MATCH($A14,'10_Data_Sources'!$A$159:$A$171,0),MATCH(E$5,'10_Data_Sources'!$B$158:$F$158,0))="","–",INDEX('10_Data_Sources'!$B$159:$F$171,MATCH($A14,'10_Data_Sources'!$A$159:$A$171,0),MATCH(E$5,'10_Data_Sources'!$B$158:$F$158,0))) -> 55.462928 | F14: =IF(INDEX('10_Data_Sources'!$B$159:$F$171,MATCH($A14,'10_Data_Sources'!$A$159:$A$171,0),MATCH(F$5,'10_Data_Sources'!$B$158:$F$158,0))="","–",INDEX('10_Data_Sources'!$B$159:$F$171,MATCH($A14,'10_Data_Sources'!$A$159:$A$171,0),MATCH(F$5,'10_Data_Sources'!$B$158:$F$158,0))) -> 40.482999
A15: dpo_days | B15: =IF(INDEX('10_Data_Sources'!$B$159:$F$171,MATCH($A15,'10_Data_Sources'!$A$159:$A$171,0),MATCH(B$5,'10_Data_Sources'!$B$158:$F$158,0))="","–",INDEX('10_Data_Sources'!$B$159:$F$171,MATCH($A15,'10_Data_Sources'!$A$159:$A$171,0),MATCH(B$5,'10_Data_Sources'!$B$158:$F$158,0))) -> 50.548758 | C15: =IF(INDEX('10_Data_Sources'!$B$159:$F$171,MATCH($A15,'10_Data_Sources'!$A$159:$A$171,0),MATCH(C$5,'10_Data_Sources'!$B$158:$F$158,0))="","–",INDEX('10_Data_Sources'!$B$159:$F$171,MATCH($A15,'10_Data_Sources'!$A$159:$A$171,0),MATCH(C$5,'10_Data_Sources'!$B$158:$F$158,0))) -> 29.52233 | D15: =IF(INDEX('10_Data_Sources'!$B$159:$F$171,MATCH($A15,'10_Data_Sources'!$A$159:$A$171,0),MATCH(D$5,'10_Data_Sources'!$B$158:$F$158,0))="","–",INDEX('10_Data_Sources'!$B$159:$F$171,MATCH($A15,'10_Data_Sources'!$A$159:$A$171,0),MATCH(D$5,'10_Data_Sources'!$B$158:$F$158,0))) -> 26.914077 | E15: =IF(INDEX('10_Data_Sources'!$B$159:$F$171,MATCH($A15,'10_Data_Sources'!$A$159:$A$171,0),MATCH(E$5,'10_Data_Sources'!$B$158:$F$158,0))="","–",INDEX('10_Data_Sources'!$B$159:$F$171,MATCH($A15,'10_Data_Sources'!$A$159:$A$171,0),MATCH(E$5,'10_Data_Sources'!$B$158:$F$158,0))) -> 24.919909 | F15: =IF(INDEX('10_Data_Sources'!$B$159:$F$171,MATCH($A15,'10_Data_Sources'!$A$159:$A$171,0),MATCH(F$5,'10_Data_Sources'!$B$158:$F$158,0))="","–",INDEX('10_Data_Sources'!$B$159:$F$171,MATCH($A15,'10_Data_Sources'!$A$159:$A$171,0),MATCH(F$5,'10_Data_Sources'!$B$158:$F$158,0))) -> 29.084423
A16: capex_pct_revenue | B16: =IF(INDEX('10_Data_Sources'!$B$159:$F$171,MATCH($A16,'10_Data_Sources'!$A$159:$A$171,0),MATCH(B$5,'10_Data_Sources'!$B$158:$F$158,0))="","–",INDEX('10_Data_Sources'!$B$159:$F$171,MATCH($A16,'10_Data_Sources'!$A$159:$A$171,0),MATCH(B$5,'10_Data_Sources'!$B$158:$F$158,0))) -> 0.089706323 | C16: =IF(INDEX('10_Data_Sources'!$B$159:$F$171,MATCH($A16,'10_Data_Sources'!$A$159:$A$171,0),MATCH(C$5,'10_Data_Sources'!$B$158:$F$158,0))="","–",INDEX('10_Data_Sources'!$B$159:$F$171,MATCH($A16,'10_Data_Sources'!$A$159:$A$171,0),MATCH(C$5,'10_Data_Sources'!$B$158:$F$158,0))) -> 0.10061828 | D16: =IF(INDEX('10_Data_Sources'!$B$159:$F$171,MATCH($A16,'10_Data_Sources'!$A$159:$A$171,0),MATCH(D$5,'10_Data_Sources'!$B$158:$F$158,0))="","–",INDEX('10_Data_Sources'!$B$159:$F$171,MATCH($A16,'10_Data_Sources'!$A$159:$A$171,0),MATCH(D$5,'10_Data_Sources'!$B$158:$F$158,0))) -> 0.080134077 | E16: =IF(INDEX('10_Data_Sources'!$B$159:$F$171,MATCH($A16,'10_Data_Sources'!$A$159:$A$171,0),MATCH(E$5,'10_Data_Sources'!$B$158:$F$158,0))="","–",INDEX('10_Data_Sources'!$B$159:$F$171,MATCH($A16,'10_Data_Sources'!$A$159:$A$171,0),MATCH(E$5,'10_Data_Sources'!$B$158:$F$158,0))) -> 0.083016666 | F16: =IF(INDEX('10_Data_Sources'!$B$159:$F$171,MATCH($A16,'10_Data_Sources'!$A$159:$A$171,0),MATCH(F$5,'10_Data_Sources'!$B$158:$F$158,0))="","–",INDEX('10_Data_Sources'!$B$159:$F$171,MATCH($A16,'10_Data_Sources'!$A$159:$A$171,0),MATCH(F$5,'10_Data_Sources'!$B$158:$F$158,0))) -> 0.076898286
A17: da_pct_revenue | B17: =IF(INDEX('10_Data_Sources'!$B$159:$F$171,MATCH($A17,'10_Data_Sources'!$A$159:$A$171,0),MATCH(B$5,'10_Data_Sources'!$B$158:$F$158,0))="","–",INDEX('10_Data_Sources'!$B$159:$F$171,MATCH($A17,'10_Data_Sources'!$A$159:$A$171,0),MATCH(B$5,'10_Data_Sources'!$B$158:$F$158,0))) -> 0.04043654 | C17: =IF(INDEX('10_Data_Sources'!$B$159:$F$171,MATCH($A17,'10_Data_Sources'!$A$159:$A$171,0),MATCH(C$5,'10_Data_Sources'!$B$158:$F$158,0))="","–",INDEX('10_Data_Sources'!$B$159:$F$171,MATCH($A17,'10_Data_Sources'!$A$159:$A$171,0),MATCH(C$5,'10_Data_Sources'!$B$158:$F$158,0))) -> 0.053274303 | D17: =IF(INDEX('10_Data_Sources'!$B$159:$F$171,MATCH($A17,'10_Data_Sources'!$A$159:$A$171,0),MATCH(D$5,'10_Data_Sources'!$B$158:$F$158,0))="","–",INDEX('10_Data_Sources'!$B$159:$F$171,MATCH($A17,'10_Data_Sources'!$A$159:$A$171,0),MATCH(D$5,'10_Data_Sources'!$B$158:$F$158,0))) -> 0.057563474 | E17: =IF(INDEX('10_Data_Sources'!$B$159:$F$171,MATCH($A17,'10_Data_Sources'!$A$159:$A$171,0),MATCH(E$5,'10_Data_Sources'!$B$158:$F$158,0))="","–",INDEX('10_Data_Sources'!$B$159:$F$171,MATCH($A17,'10_Data_Sources'!$A$159:$A$171,0),MATCH(E$5,'10_Data_Sources'!$B$158:$F$158,0))) -> 0.059463384 | F17: =IF(INDEX('10_Data_Sources'!$B$159:$F$171,MATCH($A17,'10_Data_Sources'!$A$159:$A$171,0),MATCH(F$5,'10_Data_Sources'!$B$158:$F$158,0))="","–",INDEX('10_Data_Sources'!$B$159:$F$171,MATCH($A17,'10_Data_Sources'!$A$159:$A$171,0),MATCH(F$5,'10_Data_Sources'!$B$158:$F$158,0))) -> 0.057666833
A18: sbc_pct_revenue | B18: =IF(INDEX('10_Data_Sources'!$B$159:$F$171,MATCH($A18,'10_Data_Sources'!$A$159:$A$171,0),MATCH(B$5,'10_Data_Sources'!$B$158:$F$158,0))="","–",INDEX('10_Data_Sources'!$B$159:$F$171,MATCH($A18,'10_Data_Sources'!$A$159:$A$171,0),MATCH(B$5,'10_Data_Sources'!$B$158:$F$158,0))) -> 0.19812943 | C18: =IF(INDEX('10_Data_Sources'!$B$159:$F$171,MATCH($A18,'10_Data_Sources'!$A$159:$A$171,0),MATCH(C$5,'10_Data_Sources'!$B$158:$F$158,0))="","–",INDEX('10_Data_Sources'!$B$159:$F$171,MATCH($A18,'10_Data_Sources'!$A$159:$A$171,0),MATCH(C$5,'10_Data_Sources'!$B$158:$F$158,0))) -> 0.16390241 | D18: =IF(INDEX('10_Data_Sources'!$B$159:$F$171,MATCH($A18,'10_Data_Sources'!$A$159:$A$171,0),MATCH(D$5,'10_Data_Sources'!$B$158:$F$158,0))="","–",INDEX('10_Data_Sources'!$B$159:$F$171,MATCH($A18,'10_Data_Sources'!$A$159:$A$171,0),MATCH(D$5,'10_Data_Sources'!$B$158:$F$158,0))) -> 0.10527424 | E18: =IF(INDEX('10_Data_Sources'!$B$159:$F$171,MATCH($A18,'10_Data_Sources'!$A$159:$A$171,0),MATCH(E$5,'10_Data_Sources'!$B$158:$F$158,0))="","–",INDEX('10_Data_Sources'!$B$159:$F$171,MATCH($A18,'10_Data_Sources'!$A$159:$A$171,0),MATCH(E$5,'10_Data_Sources'!$B$158:$F$158,0))) -> 0.061316064 | F18: =IF(INDEX('10_Data_Sources'!$B$159:$F$171,MATCH($A18,'10_Data_Sources'!$A$159:$A$171,0),MATCH(F$5,'10_Data_Sources'!$B$158:$F$158,0))="","–",INDEX('10_Data_Sources'!$B$159:$F$171,MATCH($A18,'10_Data_Sources'!$A$159:$A$171,0),MATCH(F$5,'10_Data_Sources'!$B$158:$F$158,0))) -> 0.03960982
A20: Section B: Selected Scenario Assumptions
A21: Scenario currently selected: | B21: ='00_Control_Panel'!C4 -> Best
A23: Driver | B23: 2026 | C23: 2027 | D23: 2028 | E23: 2029 | F23: 2030
A24: revenue_growth_pct | B24: =SUMIFS('10_Data_Sources'!$E$5:$E$154, '10_Data_Sources'!$A$5:$A$154, $A24, '10_Data_Sources'!$C$5:$C$154, '00_Control_Panel'!$C$4, '10_Data_Sources'!$D$5:$D$154, B$23) -> 0.15 | C24: =SUMIFS('10_Data_Sources'!$E$5:$E$154, '10_Data_Sources'!$A$5:$A$154, $A24, '10_Data_Sources'!$C$5:$C$154, '00_Control_Panel'!$C$4, '10_Data_Sources'!$D$5:$D$154, C$23) -> 0.14 | D24: =SUMIFS('10_Data_Sources'!$E$5:$E$154, '10_Data_Sources'!$A$5:$A$154, $A24, '10_Data_Sources'!$C$5:$C$154, '00_Control_Panel'!$C$4, '10_Data_Sources'!$D$5:$D$154, D$23) -> 0.13 | E24: =SUMIFS('10_Data_Sources'!$E$5:$E$154, '10_Data_Sources'!$A$5:$A$154, $A24, '10_Data_Sources'!$C$5:$C$154, '00_Control_Panel'!$C$4, '10_Data_Sources'!$D$5:$D$154, E$23) -> 0.12 | F24: =SUMIFS('10_Data_Sources'!$E$5:$E$154, '10_Data_Sources'!$A$5:$A$154, $A24, '10_Data_Sources'!$C$5:$C$154, '00_Control_Panel'!$C$4, '10_Data_Sources'!$D$5:$D$154, F$23) -> 0.11
A25: gross_margin_pct | B25: =SUMIFS('10_Data_Sources'!$E$5:$E$154, '10_Data_Sources'!$A$5:$A$154, $A25, '10_Data_Sources'!$C$5:$C$154, '00_Control_Panel'!$C$4, '10_Data_Sources'!$D$5:$D$154, B$23) -> 0.55 | C25: =SUMIFS('10_Data_Sources'!$E$5:$E$154, '10_Data_Sources'!$A$5:$A$154, $A25, '10_Data_Sources'!$C$5:$C$154, '00_Control_Panel'!$C$4, '10_Data_Sources'!$D$5:$D$154, C$23) -> 0.555 | D25: =SUMIFS('10_Data_Sources'!$E$5:$E$154, '10_Data_Sources'!$A$5:$A$154, $A25, '10_Data_Sources'!$C$5:$C$154, '00_Control_Panel'!$C$4, '10_Data_Sources'!$D$5:$D$154, D$23) -> 0.56 | E25: =SUMIFS('10_Data_Sources'!$E$5:$E$154, '10_Data_Sources'!$A$5:$A$154, $A25, '10_Data_Sources'!$C$5:$C$154, '00_Control_Panel'!$C$4, '10_Data_Sources'!$D$5:$D$154, E$23) -> 0.565 | F25: =SUMIFS('10_Data_Sources'!$E$5:$E$154, '10_Data_Sources'!$A$5:$A$154, $A25, '10_Data_Sources'!$C$5:$C$154, '00_Control_Panel'!$C$4, '10_Data_Sources'!$D$5:$D$154, F$23) -> 0.57
A26: sga_pct_revenue | B26: =SUMIFS('10_Data_Sources'!$E$5:$E$154, '10_Data_Sources'!$A$5:$A$154, $A26, '10_Data_Sources'!$C$5:$C$154, '00_Control_Panel'!$C$4, '10_Data_Sources'!$D$5:$D$154, B$23) -> 0.53 | C26: =SUMIFS('10_Data_Sources'!$E$5:$E$154, '10_Data_Sources'!$A$5:$A$154, $A26, '10_Data_Sources'!$C$5:$C$154, '00_Control_Panel'!$C$4, '10_Data_Sources'!$D$5:$D$154, C$23) -> 0.5075 | D26: =SUMIFS('10_Data_Sources'!$E$5:$E$154, '10_Data_Sources'!$A$5:$A$154, $A26, '10_Data_Sources'!$C$5:$C$154, '00_Control_Panel'!$C$4, '10_Data_Sources'!$D$5:$D$154, D$23) -> 0.485 | E26: =SUMIFS('10_Data_Sources'!$E$5:$E$154, '10_Data_Sources'!$A$5:$A$154, $A26, '10_Data_Sources'!$C$5:$C$154, '00_Control_Panel'!$C$4, '10_Data_Sources'!$D$5:$D$154, E$23) -> 0.4625 | F26: =SUMIFS('10_Data_Sources'!$E$5:$E$154, '10_Data_Sources'!$A$5:$A$154, $A26, '10_Data_Sources'!$C$5:$C$154, '00_Control_Panel'!$C$4, '10_Data_Sources'!$D$5:$D$154, F$23) -> 0.44
A27: effective_tax_rate_pct | B27: =SUMIFS('10_Data_Sources'!$E$5:$E$154, '10_Data_Sources'!$A$5:$A$154, $A27, '10_Data_Sources'!$C$5:$C$154, '00_Control_Panel'!$C$4, '10_Data_Sources'!$D$5:$D$154, B$23) -> 0.05 | C27: =SUMIFS('10_Data_Sources'!$E$5:$E$154, '10_Data_Sources'!$A$5:$A$154, $A27, '10_Data_Sources'!$C$5:$C$154, '00_Control_Panel'!$C$4, '10_Data_Sources'!$D$5:$D$154, C$23) -> 0.0875 | D27: =SUMIFS('10_Data_Sources'!$E$5:$E$154, '10_Data_Sources'!$A$5:$A$154, $A27, '10_Data_Sources'!$C$5:$C$154, '00_Control_Panel'!$C$4, '10_Data_Sources'!$D$5:$D$154, D$23) -> 0.125 | E27: =SUMIFS('10_Data_Sources'!$E$5:$E$154, '10_Data_Sources'!$A$5:$A$154, $A27, '10_Data_Sources'!$C$5:$C$154, '00_Control_Panel'!$C$4, '10_Data_Sources'!$D$5:$D$154, E$23) -> 0.1625 | F27: =SUMIFS('10_Data_Sources'!$E$5:$E$154, '10_Data_Sources'!$A$5:$A$154, $A27, '10_Data_Sources'!$C$5:$C$154, '00_Control_Panel'!$C$4, '10_Data_Sources'!$D$5:$D$154, F$23) -> 0.2
A28: dso_days | B28: =SUMIFS('10_Data_Sources'!$E$5:$E$154, '10_Data_Sources'!$A$5:$A$154, $A28, '10_Data_Sources'!$C$5:$C$154, '00_Control_Panel'!$C$4, '10_Data_Sources'!$D$5:$D$154, B$23) -> 1.2 | C28: =SUMIFS('10_Data_Sources'!$E$5:$E$154, '10_Data_Sources'!$A$5:$A$154, $A28, '10_Data_Sources'!$C$5:$C$154, '00_Control_Panel'!$C$4, '10_Data_Sources'!$D$5:$D$154, C$23) -> 1.2 | D28: =SUMIFS('10_Data_Sources'!$E$5:$E$154, '10_Data_Sources'!$A$5:$A$154, $A28, '10_Data_Sources'!$C$5:$C$154, '00_Control_Panel'!$C$4, '10_Data_Sources'!$D$5:$D$154, D$23) -> 1.2 | E28: =SUMIFS('10_Data_Sources'!$E$5:$E$154, '10_Data_Sources'!$A$5:$A$154, $A28, '10_Data_Sources'!$C$5:$C$154, '00_Control_Panel'!$C$4, '10_Data_Sources'!$D$5:$D$154, E$23) -> 1.2 | F28: =SUMIFS('10_Data_Sources'!$E$5:$E$154, '10_Data_Sources'!$A$5:$A$154, $A28, '10_Data_Sources'!$C$5:$C$154, '00_Control_Panel'!$C$4, '10_Data_Sources'!$D$5:$D$154, F$23) -> 1.2
A29: dio_days | B29: =SUMIFS('10_Data_Sources'!$E$5:$E$154, '10_Data_Sources'!$A$5:$A$154, $A29, '10_Data_Sources'!$C$5:$C$154, '00_Control_Panel'!$C$4, '10_Data_Sources'!$D$5:$D$154, B$23) -> 38 | C29: =SUMIFS('10_Data_Sources'!$E$5:$E$154, '10_Data_Sources'!$A$5:$A$154, $A29, '10_Data_Sources'!$C$5:$C$154, '00_Control_Panel'!$C$4, '10_Data_Sources'!$D$5:$D$154, C$23) -> 35 | D29: =SUMIFS('10_Data_Sources'!$E$5:$E$154, '10_Data_Sources'!$A$5:$A$154, $A29, '10_Data_Sources'!$C$5:$C$154, '00_Control_Panel'!$C$4, '10_Data_Sources'!$D$5:$D$154, D$23) -> 32 | E29: =SUMIFS('10_Data_Sources'!$E$5:$E$154, '10_Data_Sources'!$A$5:$A$154, $A29, '10_Data_Sources'!$C$5:$C$154, '00_Control_Panel'!$C$4, '10_Data_Sources'!$D$5:$D$154, E$23) -> 29 | F29: =SUMIFS('10_Data_Sources'!$E$5:$E$154, '10_Data_Sources'!$A$5:$A$154, $A29, '10_Data_Sources'!$C$5:$C$154, '00_Control_Panel'!$C$4, '10_Data_Sources'!$D$5:$D$154, F$23) -> 26
A30: dpo_days | B30: =SUMIFS('10_Data_Sources'!$E$5:$E$154, '10_Data_Sources'!$A$5:$A$154, $A30, '10_Data_Sources'!$C$5:$C$154, '00_Control_Panel'!$C$4, '10_Data_Sources'!$D$5:$D$154, B$23) -> 30 | C30: =SUMIFS('10_Data_Sources'!$E$5:$E$154, '10_Data_Sources'!$A$5:$A$154, $A30, '10_Data_Sources'!$C$5:$C$154, '00_Control_Panel'!$C$4, '10_Data_Sources'!$D$5:$D$154, C$23) -> 31 | D30: =SUMIFS('10_Data_Sources'!$E$5:$E$154, '10_Data_Sources'!$A$5:$A$154, $A30, '10_Data_Sources'!$C$5:$C$154, '00_Control_Panel'!$C$4, '10_Data_Sources'!$D$5:$D$154, D$23) -> 32 | E30: =SUMIFS('10_Data_Sources'!$E$5:$E$154, '10_Data_Sources'!$A$5:$A$154, $A30, '10_Data_Sources'!$C$5:$C$154, '00_Control_Panel'!$C$4, '10_Data_Sources'!$D$5:$D$154, E$23) -> 33 | F30: =SUMIFS('10_Data_Sources'!$E$5:$E$154, '10_Data_Sources'!$A$5:$A$154, $A30, '10_Data_Sources'!$C$5:$C$154, '00_Control_Panel'!$C$4, '10_Data_Sources'!$D$5:$D$154, F$23) -> 34
A31: capex_pct_revenue | B31: =SUMIFS('10_Data_Sources'!$E$5:$E$154, '10_Data_Sources'!$A$5:$A$154, $A31, '10_Data_Sources'!$C$5:$C$154, '00_Control_Panel'!$C$4, '10_Data_Sources'!$D$5:$D$154, B$23) -> 0.075 | C31: =SUMIFS('10_Data_Sources'!$E$5:$E$154, '10_Data_Sources'!$A$5:$A$154, $A31, '10_Data_Sources'!$C$5:$C$154, '00_Control_Panel'!$C$4, '10_Data_Sources'!$D$5:$D$154, C$23) -> 0.07375 | D31: =SUMIFS('10_Data_Sources'!$E$5:$E$154, '10_Data_Sources'!$A$5:$A$154, $A31, '10_Data_Sources'!$C$5:$C$154, '00_Control_Panel'!$C$4, '10_Data_Sources'!$D$5:$D$154, D$23) -> 0.0725 | E31: =SUMIFS('10_Data_Sources'!$E$5:$E$154, '10_Data_Sources'!$A$5:$A$154, $A31, '10_Data_Sources'!$C$5:$C$154, '00_Control_Panel'!$C$4, '10_Data_Sources'!$D$5:$D$154, E$23) -> 0.07125 | F31: =SUMIFS('10_Data_Sources'!$E$5:$E$154, '10_Data_Sources'!$A$5:$A$154, $A31, '10_Data_Sources'!$C$5:$C$154, '00_Control_Panel'!$C$4, '10_Data_Sources'!$D$5:$D$154, F$23) -> 0.07
A32: da_pct_revenue | B32: =SUMIFS('10_Data_Sources'!$E$5:$E$154, '10_Data_Sources'!$A$5:$A$154, $A32, '10_Data_Sources'!$C$5:$C$154, '00_Control_Panel'!$C$4, '10_Data_Sources'!$D$5:$D$154, B$23) -> 0.056 | C32: =SUMIFS('10_Data_Sources'!$E$5:$E$154, '10_Data_Sources'!$A$5:$A$154, $A32, '10_Data_Sources'!$C$5:$C$154, '00_Control_Panel'!$C$4, '10_Data_Sources'!$D$5:$D$154, C$23) -> 0.0555 | D32: =SUMIFS('10_Data_Sources'!$E$5:$E$154, '10_Data_Sources'!$A$5:$A$154, $A32, '10_Data_Sources'!$C$5:$C$154, '00_Control_Panel'!$C$4, '10_Data_Sources'!$D$5:$D$154, D$23) -> 0.055 | E32: =SUMIFS('10_Data_Sources'!$E$5:$E$154, '10_Data_Sources'!$A$5:$A$154, $A32, '10_Data_Sources'!$C$5:$C$154, '00_Control_Panel'!$C$4, '10_Data_Sources'!$D$5:$D$154, E$23) -> 0.0545 | F32: =SUMIFS('10_Data_Sources'!$E$5:$E$154, '10_Data_Sources'!$A$5:$A$154, $A32, '10_Data_Sources'!$C$5:$C$154, '00_Control_Panel'!$C$4, '10_Data_Sources'!$D$5:$D$154, F$23) -> 0.054
A33: sbc_pct_revenue | B33: =SUMIFS('10_Data_Sources'!$E$5:$E$154, '10_Data_Sources'!$A$5:$A$154, $A33, '10_Data_Sources'!$C$5:$C$154, '00_Control_Panel'!$C$4, '10_Data_Sources'!$D$5:$D$154, B$23) -> 0.032 | C33: =SUMIFS('10_Data_Sources'!$E$5:$E$154, '10_Data_Sources'!$A$5:$A$154, $A33, '10_Data_Sources'!$C$5:$C$154, '00_Control_Panel'!$C$4, '10_Data_Sources'!$D$5:$D$154, C$23) -> 0.0295 | D33: =SUMIFS('10_Data_Sources'!$E$5:$E$154, '10_Data_Sources'!$A$5:$A$154, $A33, '10_Data_Sources'!$C$5:$C$154, '00_Control_Panel'!$C$4, '10_Data_Sources'!$D$5:$D$154, D$23) -> 0.027 | E33: =SUMIFS('10_Data_Sources'!$E$5:$E$154, '10_Data_Sources'!$A$5:$A$154, $A33, '10_Data_Sources'!$C$5:$C$154, '00_Control_Panel'!$C$4, '10_Data_Sources'!$D$5:$D$154, E$23) -> 0.0245 | F33: =SUMIFS('10_Data_Sources'!$E$5:$E$154, '10_Data_Sources'!$A$5:$A$154, $A33, '10_Data_Sources'!$C$5:$C$154, '00_Control_Panel'!$C$4, '10_Data_Sources'!$D$5:$D$154, F$23) -> 0.022

Sheet 02_Historical_IS_BS_CF
A1: Historical Financials (FY2021 - FY2025, $ in thousands)
A3: Income Statement
A4: Line Item | B4: 2021 | C4: =B4+1 -> 2022 | D4: =C4+1 -> 2023 | E4: =D4+1 -> 2024 | F4: =E4+1 -> 2025
A5: Net revenue | B5: 540798 | C5: 598112 | D5: 669765 | E5: 771315 | F5: 871905
A6: Cost of goods sold | B6: 223049 | C6: 257050 | D6: 304541 | E6: 344481 | F6: 401326
A7: Gross profit | B7: =B5-B6 -> 317749 | C7: =C5-C6 -> 341062 | D7: =D5-D6 -> 365224 | E7: =E5-E6 -> 426834 | F7: =F5-F6 -> 470579
A8: Selling, general, and administrative expenses | B8: 461410 | C8: 452265 | D8: 437220 | E8: 456946 | F8: 475915
A9: Operating income (loss) | B9: =B7-B8 -> -143661 | C9: =C7-C8 -> -111203 | D9: =D7-D8 -> -71996 | E9: =E7-E8 -> -30112 | F9: =F7-F8 -> -5336
A10: Interest and other income (loss), net | B10: -347 | C10: 1307 | D10: 9232 | E10: 10597 | F10: 8379
A11: Income (loss) before income taxes | B11: =B9+B10 -> -144008 | C11: =C9+C10 -> -109896 | D11: =D9+D10 -> -62764 | E11: =E9+E10 -> -19515 | F11: =F9+F10 -> 3043
A12: Provision for income taxes | B12: 263 | C12: 497 | D12: 433 | E12: 875 | F12: 1402
A13: Net income (loss) | B13: =B11-B12 -> -144271 | C13: =C11-C12 -> -110393 | D13: =D11-D12 -> -63197 | E13: =E11-E12 -> -20390 | F13: =F11-F12 -> 1641
A16: QC Check: Formula vs. Reported
A17: Gross profit check | B17: =B7-B21 -> 0 | C17: =C7-C21 -> 0 | D17: =D7-D21 -> 0 | E17: =E7-E21 -> 0 | F17: =F7-F21 -> 0
A18: Operating income check | B18: =B9-B22 -> 0 | C18: =C9-C22 -> 0 | D18: =D9-D22 -> 0 | E18: =E9-E22 -> 0 | F18: =F9-F22 -> 0
A19: Net income check | B19: =B13-B23 -> 0 | C19: =C13-C23 -> 0 | D19: =D13-D23 -> 0 | E19: =E13-E23 -> 0 | F19: =F13-F23 -> 0
A21: Reported: Gross profit | B21: 317749 | C21: 341062 | D21: 365224 | E21: 426834 | F21: 470579
A22: Reported: Operating income | B22: -143661 | C22: -111203 | D22: -71996 | E22: -30112 | F22: -5336
A23: Reported: Net income | B23: -144271 | C23: -110393 | D23: -63197 | E23: -20390 | F23: 1641
A26: Balance Sheet
A27: Line Item | B27: 2021 | C27: =B27+1 -> 2022 | D27: =C27+1 -> 2023 | E27: =D27+1 -> 2024 | F27: =E27+1 -> 2025
A28: Cash and cash equivalents | B28: 256416 | C28: 208585 | D28: 216894 | E28: 254161 | F28: 286358
A29: Accounts receivable, net | B29: 992 | C29: 1435 | D29: 1779 | E29: 1948 | F29: 3285
A30: Inventory | B30: 57095 | C30: 68848 | D30: 62234 | E30: 52345 | F30: 44512
A31: Prepaid expenses and other current assets | B31: 13477 | C31: 15700 | D31: 17712 | E31: 17592 | F31: 18283
A32: Total current assets | B32: =SUM(B28:B31) -> 327980 | C32: =SUM(C28:C31) -> 294568 | D32: =SUM(D28:D31) -> 298619 | E32: =SUM(E28:E31) -> 326046 | F32: =SUM(F28:F31) -> 352438
A33: Property and equipment, net | B33: 112195 | C33: 138628 | D33: 152332 | E33: 170464 | F33: 187448
A34: Right-of-use lease assets | B34: 0 | C34: 127014 | D34: 122305 | E34: 171284 | F34: 170805
A35: Other assets | B35: 471 | C35: 8497 | D35: 7056 | E35: 8696 | F35: 10228
A36: Total assets | B36: =B32+B33+B34+B35 -> 440646 | C36: =C32+C33+C34+C35 -> 568707 | D36: =D32+D33+D34+D35 -> 580312 | E36: =E32+E33+E34+E35 -> 676490 | F36: =F32+F33+F34+F35 -> 720919
A37: Accounts payable | B37: 30890 | C37: 20791 | D37: 22456 | E37: 23519 | F37: 31979
A38: Accrued expenses | B38: 60840 | C38: 58222 | D38: 46320 | E38: 51609 | F38: 49225
A39: Deferred revenue | B39: 22073 | C39: 25628 | D39: 31617 | E39: 32358 | F39: 33869
A40: Current lease liabilities | B40: 0 | C40: 22546 | D40: 24286 | E40: 20235 | F40: 31399
A41: Other current liabilities | B41: 4301 | C41: 2370 | D41: 2411 | E41: 2633 | F41: 3658
A42: Total current liabilities | B42: =SUM(B37:B41) -> 118104 | C42: =SUM(C37:C41) -> 129557 | D42: =SUM(D37:D41) -> 127090 | E42: =SUM(E37:E41) -> 130354 | F42: =SUM(F37:F41) -> 150130
A43: Non-current lease liabilities | B43: 0 | C43: 150832 | D43: 150171 | E43: 205120 | F43: 201749
A44: Deferred rent | B44: 36544 | C44: 0 | D44: 0 | E44: 0 | F44: 0
A45: Other liabilities | B45: 0 | C45: 1672 | D45: 1264 | E45: 943 | F45: 1310
A46: Total liabilities | B46: =B42+B43+B44+B45 -> 154648 | C46: =C42+C43+C44+C45 -> 282061 | D46: =D42+D43+D44+D45 -> 278525 | E46: =E42+E43+E44+E45 -> 336417 | F46: =F42+F43+F44+F45 -> 353189
A47: Common Stock | B47: 0 | C47: 12 | D47: 12 | E47: 12 | F47: 12
A48: Additional paid-in capital | B48: 779212 | C48: 890915 | D48: 970135 | E48: 1029220 | F48: 1054779
A49: Accumulated deficit | B49: -493241 | C49: -603634 | D49: -666831 | E49: -687221 | F49: -685580
A50: Accumulated other comprehensive income | B50: 16 | C50: -647 | D50: -1529 | E50: -1938 | F50: -1481
A51: Total stockholders' equity | B51: =SUM(B47:B50) -> 285987 | C51: =SUM(C47:C50) -> 286646 | D51: =SUM(D47:D50) -> 301787 | E51: =SUM(E47:E50) -> 340073 | F51: =SUM(F47:F50) -> 367730
A52: Total liabilities and stockholders' equity | B52: =B46+B51 -> 440635 | C52: =C46+C51 -> 568707 | D52: =D46+D51 -> 580312 | E52: =E46+E51 -> 676490 | F52: =F46+F51 -> 720919
A54: QC Check: Formula vs. Reported
A55: Current assets check | B55: =B32-B62 -> 0 | C55: =C32-C62 -> 0 | D55: =D32-D62 -> 0 | E55: =E32-E62 -> 0 | F55: =F32-F62 -> 0
A56: Total assets check | B56: =B36-B63 -> 0 | C56: =C36-C63 -> 0 | D56: =D36-D63 -> 0 | E56: =E36-E63 -> 0 | F56: =F36-F63 -> 0
A57: Current liabilities check | B57: =B42-B64 -> 0 | C57: =C42-C64 -> 0 | D57: =D42-D64 -> 0 | E57: =E42-E64 -> 0 | F57: =F42-F64 -> 0
A58: Total liabilities check | B58: =B46-B65 -> 0 | C58: =C46-C65 -> 0 | D58: =D46-D65 -> 0 | E58: =E46-E65 -> 0 | F58: =F46-F65 -> 0
A59: Equity check | B59: =B51-B66 -> -11 | C59: =C51-C66 -> 0 | D59: =D51-D66 -> 0 | E59: =E51-E66 -> 0 | F59: =F51-F66 -> 0
A60: Balance sheet ties | B60: =B36-B52 -> 11 | C60: =C36-C52 -> 0 | D60: =D36-D52 -> 0 | E60: =E36-E52 -> 0 | F60: =F36-F52 -> 0
A62: Reported: Total current assets | B62: 327980 | C62: 294568 | D62: 298619 | E62: 326046 | F62: 352438
A63: Reported: Total assets | B63: 440646 | C63: 568707 | D63: 580312 | E63: 676490 | F63: 720919
A64: Reported: Total current liabilities | B64: 118104 | C64: 129557 | D64: 127090 | E64: 130354 | F64: 150130
A65: Reported: Total liabilities | B65: 154648 | C65: 282061 | D65: 278525 | E65: 336417 | F65: 353189
A66: Reported: Total stockholders' equity | B66: 285998 | C66: 286646 | D66: 301787 | E66: 340073 | F66: 367730
A68: Cash Flow Statement
A69: Line Item | B69: 2021 | C69: =B69+1 -> 2022 | D69: =C69+1 -> 2023 | E69: =D69+1 -> 2024 | F69: =E69+1 -> 2025
A70: Net income (loss) | B70: =B13 -> -144271 | C70: =C13 -> -110393 | D70: =D13 -> -63197 | E70: =E13 -> -20390 | F70: =F13 -> 1641
A71: Depreciation and amortization | B71: 21868 | C71: 31864 | D71: 38554 | E71: 45865 | F71: 50280
A72: Stock-based compensation | B72: 107148 | C72: 98032 | D72: 70509 | E72: 47294 | F72: 34536
A73: Amortization of cloud-based software implementation costs | B73: 0 | C73: 0 | D73: 2895 | E73: 3704 | F73: 3405
A74: Asset impairment charges | B74: 0 | C74: 1647 | D74: 3230 | E74: 816 | F74: 557
A75: Non-cash charitable contribution | B75: 7757 | C75: 3770 | D75: 3191 | E75: 2196 | F75: 2821
A76: Deferred rent (non-cash) | B76: 8547 | C76: 0 | D76: 0 | F76: 0
A77: Accounts receivable, net | B77: -392 | C77: -451 | D77: -345 | E77: -169 | F77: -1337
A78: Inventory | B78: -18624 | C78: -11794 | D78: 6614 | E78: 9889 | F78: 7833
A79: Prepaid expenses and other assets | B79: -6887 | C79: -10287 | D79: -3276 | E79: -3233 | F79: -5631
A80: Accounts payable | B80: -11114 | C80: -7943 | D80: 1633 | E80: 689 | F80: 8500
A81: Accrued expenses | B81: 9486 | C81: 2748 | D81: -8898 | E81: 9521 | F81: -2691
A82: Deferred revenue | B82: -4478 | C82: 3583 | D82: 5989 | E82: 741 | F82: 1511
A83: Other current liabilities | B83: 579 | C83: 537 | D83: 41 | E83: 0 | F83: 0
A84: Other liabilities | B84: -1613 | C84: 1672 | D84: -408 | E84: -99 | F84: 1088
A85: Lease assets and liabilities | B85: 0 | C85: 7385 | D85: 4459 | E85: 1920 | F85: 8272
A86: Net cash provided by (used in) operating activities | B86: =SUM(B70:B85) -> -31994 | C86: =SUM(C70:C85) -> 10370 | D86: =SUM(D70:D85) -> 60991 | E86: =SUM(E70:E85) -> 98744 | F86: =SUM(F70:F85) -> 110785
A87: Purchases of property and equipment | B87: -48513 | C87: -60181 | D87: -53671 | E87: -64032 | F87: -67048
A88: Investment in optical equipment company | B88: 0 | C88: 0 | D88: -1000 | E88: -2000 | F88: 0
A89: Net cash used in investing activities | B89: =SUM(B87:B88) -> -48513 | C89: =SUM(C87:C88) -> -60181 | D89: =SUM(D87:D88) -> -54671 | E89: =SUM(E87:E88) -> -66032 | F89: =SUM(F87:F88) -> -67048
A90: Net cash provided by (used in) financing activities | B90: 22999 | C90: 3291 | D90: 2871 | E90: 4961 | F90: -11997
A91: Effect of exchange rates on cash | B91: -161 | C91: -1311 | D91: -882 | E91: -404 | F91: 457
A92: Net increase (decrease) in cash | B92: =B86+B89+B90+B91 -> -57669 | C92: =C86+C89+C90+C91 -> -47831 | D92: =D86+D89+D90+D91 -> 8309 | E92: =E86+E89+E90+E91 -> 37269 | F92: =F86+F89+F90+F91 -> 32197
A93: Cash - beginning of year | B93: 314085 | C93: =B95 -> 256416 | D93: =C95 -> 208585 | E93: =D95 -> 216894 | F93: =E95 -> 254163
A95: Cash - end of year | B95: =B92+B93 -> 256416 | C95: =C92+C93 -> 208585 | D95: =D92+D93 -> 216894 | E95: =E92+E93 -> 254163 | F95: =F92+F93 -> 286360
A97: QC Check: Formula vs. Reported
A98: Operating cash flow check | B98: =B86-B102 -> 0 | C98: =C86-C102 -> 0 | D98: =D86-D102 -> 0 | E98: =E86-E102 -> 0 | F98: =F86-F102 -> 0
A99: Investing cash flow check | B99: =B89-B103 -> 0 | C99: =C89-C103 -> 0 | D99: =D89-D103 -> 0 | E99: =E89-E103 -> 0 | F99: =F89-F103 -> 0
A100: Net change in cash check | B100: =B92-B104 -> 0 | C100: =C92-C104 -> 0 | D100: =D92-D104 -> 0 | E100: =E92-E104 -> 2 | F100: =F92-F104 -> 0
A102: Reported: Net cash from operating activities | B102: -31994 | C102: 10370 | D102: 60991 | E102: 98744 | F102: 110785
A103: Reported: Net cash used in investing activities | B103: -48513 | C103: -60181 | D103: -54671 | E103: -66032 | F103: -67048
A104: Reported: Net increase (decrease) in cash | B104: -57669 | C104: -47831 | D104: 8309 | E104: 37267 | F104: 32197
A106: GOLDEN TIE: CF ending cash = BS cash | B106: =B95-B28 -> 0 | C106: =C95-C28 -> 0 | D106: =D95-D28 -> 0 | E106: =E95-E28 -> 2 | F106: =F95-F28 -> 2

Sheet 03_Forecast_IS
A1: Forecast Income Statement (FY2026 - FY2030, $ in thousands)
A3: Scenario: | B3: ='00_Control_Panel'!C4 -> Best
A5: Line Item | B5: 2026 | C5: =B5+1 -> 2027 | D5: =C5+1 -> 2028 | E5: =D5+1 -> 2029 | F5: =E5+1 -> 2030
A6: Net revenue | B6: ='02_Historical_IS_BS_CF'!F5*(1+'01_Assumptions'!B24) -> 1002690.7 | C6: =B6*(1+'01_Assumptions'!C24) -> 1143067.5 | D6: =C6*(1+'01_Assumptions'!D24) -> 1291666.2 | E6: =D6*(1+'01_Assumptions'!E24) -> 1446666.2 | F6: =E6*(1+'01_Assumptions'!F24) -> 1605799.4
A7: Cost of goods sold | B7: =B6*(1-'01_Assumptions'!B25) -> 451210.84 | C7: =C6*(1-'01_Assumptions'!C25) -> 508665.02 | D7: =D6*(1-'01_Assumptions'!D25) -> 568333.14 | E7: =E6*(1-'01_Assumptions'!E25) -> 629299.78 | F7: =F6*(1-'01_Assumptions'!F25) -> 690493.76
A8: Gross profit | B8: =B6-B7 -> 551479.91 | C8: =C6-C7 -> 634402.44 | D8: =D6-D7 -> 723333.09 | E8: =E6-E7 -> 817366.39 | F8: =F6-F7 -> 915305.69
A9: Selling, general, and administrative expenses | B9: =B6*'01_Assumptions'!B26 -> 531426.1 | C9: =C6*'01_Assumptions'!C26 -> 580106.73 | D9: =D6*'01_Assumptions'!D26 -> 626458.12 | E9: =E6*'01_Assumptions'!E26 -> 669083.1 | F9: =F6*'01_Assumptions'!F26 -> 706551.76
A10: Operating income (loss) | B10: =B8-B9 -> 20053.815 | C10: =C8-C9 -> 54295.704 | D10: =D8-D9 -> 96874.967 | E10: =E8-E9 -> 148283.28 | F10: =F8-F9 -> 208753.93
A11: Interest and other income (loss), net | B11: ='02_Historical_IS_BS_CF'!$F$10 -> 8379 | C11: ='02_Historical_IS_BS_CF'!$F$10 -> 8379 | D11: ='02_Historical_IS_BS_CF'!$F$10 -> 8379 | E11: ='02_Historical_IS_BS_CF'!$F$10 -> 8379 | F11: ='02_Historical_IS_BS_CF'!$F$10 -> 8379
A12: Income (loss) before income taxes | B12: =B10+B11 -> 28432.815 | C12: =C10+C11 -> 62674.704 | D12: =D10+D11 -> 105253.97 | E12: =E10+E11 -> 156662.28 | F12: =F10+F11 -> 217132.93
A13: Provision for income taxes | B13: =IF(B12<=0,0,B12*'01_Assumptions'!B27) -> 1421.6408 | C13: =IF(C12<=0,0,C12*'01_Assumptions'!C27) -> 5484.0366 | D13: =IF(D12<=0,0,D12*'01_Assumptions'!D27) -> 13156.746 | E13: =IF(E12<=0,0,E12*'01_Assumptions'!E27) -> 25457.621 | F13: =IF(F12<=0,0,F12*'01_Assumptions'!F27) -> 43426.586
A14: Net income (loss) | B14: =B12-B13 -> 27011.174 | C14: =C12-C13 -> 57190.668 | D14: =D12-D13 -> 92097.221 | E14: =E12-E13 -> 131204.66 | F14: =F12-F13 -> 173706.34

Sheet 04_Forecast_BS
A1: Forecast Balance Sheet (FY2026 - FY2030, $ in thousands)
A3: Scenario: | B3: ='00_Control_Panel'!C4 -> Best
A5: Assets
A6: Line Item | B6: 2026 | C6: =B6+1 -> 2027 | D6: =C6+1 -> 2028 | E6: =D6+1 -> 2029 | F6: =E6+1 -> 2030
A7: Cash and cash equivalents | B7: ='05_Forecast_CF'!B20 -> 329036.08 | C7: ='05_Forecast_CF'!C20 -> 402939.89 | D7: ='05_Forecast_CF'!D20 -> 512393.81 | E7: ='05_Forecast_CF'!E20 -> 661196.98 | F7: ='05_Forecast_CF'!F20 -> 852252.61
A8: Accounts receivable, net | B8: ='06_Supporting_Schedules'!B7 -> 3296.5175 | C8: ='06_Supporting_Schedules'!C7 -> 3758.03 | D8: ='06_Supporting_Schedules'!D7 -> 4246.5739 | E8: ='06_Supporting_Schedules'!E7 -> 4756.1628 | F8: ='06_Supporting_Schedules'!F7 -> 5279.3407
A9: Inventory | B9: ='06_Supporting_Schedules'!B8 -> 46975.375 | C9: ='06_Supporting_Schedules'!C8 -> 48776.098 | D9: ='06_Supporting_Schedules'!D8 -> 49826.467 | E9: ='06_Supporting_Schedules'!E8 -> 49999.161 | F9: ='06_Supporting_Schedules'!F8 -> 49185.857
A10: Prepaid expenses and other current assets | B10: ='02_Historical_IS_BS_CF'!$F$31 -> 18283 | C10: ='02_Historical_IS_BS_CF'!$F$31 -> 18283 | D10: ='02_Historical_IS_BS_CF'!$F$31 -> 18283 | E10: ='02_Historical_IS_BS_CF'!$F$31 -> 18283 | F10: ='02_Historical_IS_BS_CF'!$F$31 -> 18283
A11: Total current assets | B11: =B7+B8+B9+B10 -> 397590.98 | C11: =C7+C8+C9+C10 -> 473757.02 | D11: =D7+D8+D9+D10 -> 584749.85 | E11: =E7+E8+E9+E10 -> 734235.3 | F11: =F7+F8+F9+F10 -> 925000.81
A12: Property and equipment, net | B12: ='06_Supporting_Schedules'!B17 -> 206499.12 | C12: ='06_Supporting_Schedules'!C17 -> 227360.11 | D12: ='06_Supporting_Schedules'!D17 -> 249964.26 | E12: ='06_Supporting_Schedules'!E17 -> 274195.92 | F12: ='06_Supporting_Schedules'!F17 -> 299888.71
A13: Right-of-use lease assets | B13: ='02_Historical_IS_BS_CF'!$F$34 -> 170805 | C13: ='02_Historical_IS_BS_CF'!$F$34 -> 170805 | D13: ='02_Historical_IS_BS_CF'!$F$34 -> 170805 | E13: ='02_Historical_IS_BS_CF'!$F$34 -> 170805 | F13: ='02_Historical_IS_BS_CF'!$F$34 -> 170805
A14: Other assets | B14: ='02_Historical_IS_BS_CF'!$F$35 -> 10228 | C14: ='02_Historical_IS_BS_CF'!$F$35 -> 10228 | D14: ='02_Historical_IS_BS_CF'!$F$35 -> 10228 | E14: ='02_Historical_IS_BS_CF'!$F$35 -> 10228 | F14: ='02_Historical_IS_BS_CF'!$F$35 -> 10228
A15: Total assets | B15: =B11+B12+B13+B14 -> 785123.1 | C15: =C11+C12+C13+C14 -> 882150.12 | D15: =D11+D12+D13+D14 -> 1015747.1 | E15: =E11+E12+E13+E14 -> 1189464.2 | F15: =F11+F12+F13+F14 -> 1405922.5
A17: Liabilities and Equity
A18: Line Item | B18: 2026 | C18: =B18+1 -> 2027 | D18: =C18+1 -> 2028 | E18: =D18+1 -> 2029 | F18: =E18+1 -> 2030
A19: Accounts payable | B19: ='06_Supporting_Schedules'!B9 -> 37085.822 | C19: ='06_Supporting_Schedules'!C9 -> 43201.686 | D19: ='06_Supporting_Schedules'!D9 -> 49826.467 | E19: ='06_Supporting_Schedules'!E9 -> 56895.597 | F19: ='06_Supporting_Schedules'!F9 -> 64319.967
A20: Accrued expenses | B20: ='02_Historical_IS_BS_CF'!$F$38 -> 49225 | C20: ='02_Historical_IS_BS_CF'!$F$38 -> 49225 | D20: ='02_Historical_IS_BS_CF'!$F$38 -> 49225 | E20: ='02_Historical_IS_BS_CF'!$F$38 -> 49225 | F20: ='02_Historical_IS_BS_CF'!$F$38 -> 49225
A21: Deferred revenue | B21: ='02_Historical_IS_BS_CF'!$F$39 -> 33869 | C21: ='02_Historical_IS_BS_CF'!$F$39 -> 33869 | D21: ='02_Historical_IS_BS_CF'!$F$39 -> 33869 | E21: ='02_Historical_IS_BS_CF'!$F$39 -> 33869 | F21: ='02_Historical_IS_BS_CF'!$F$39 -> 33869
A22: Current lease liabilities | B22: ='02_Historical_IS_BS_CF'!$F$40 -> 31399 | C22: ='02_Historical_IS_BS_CF'!$F$40 -> 31399 | D22: ='02_Historical_IS_BS_CF'!$F$40 -> 31399 | E22: ='02_Historical_IS_BS_CF'!$F$40 -> 31399 | F22: ='02_Historical_IS_BS_CF'!$F$40 -> 31399
A23: Other current liabilities | B23: ='02_Historical_IS_BS_CF'!$F$41 -> 3658 | C23: ='02_Historical_IS_BS_CF'!$F$41 -> 3658 | D23: ='02_Historical_IS_BS_CF'!$F$41 -> 3658 | E23: ='02_Historical_IS_BS_CF'!$F$41 -> 3658 | F23: ='02_Historical_IS_BS_CF'!$F$41 -> 3658
A24: Total current liabilities | B24: =SUM(B19:B23) -> 155236.82 | C24: =SUM(C19:C23) -> 161352.69 | D24: =SUM(D19:D23) -> 167977.47 | E24: =SUM(E19:E23) -> 175046.6 | F24: =SUM(F19:F23) -> 182470.97
A25: Non-current lease liabilities | B25: ='02_Historical_IS_BS_CF'!$F$43 -> 201749 | C25: ='02_Historical_IS_BS_CF'!$F$43 -> 201749 | D25: ='02_Historical_IS_BS_CF'!$F$43 -> 201749 | E25: ='02_Historical_IS_BS_CF'!$F$43 -> 201749 | F25: ='02_Historical_IS_BS_CF'!$F$43 -> 201749
A26: Deferred rent | B26: ='02_Historical_IS_BS_CF'!$F$44 -> 0 | C26: ='02_Historical_IS_BS_CF'!$F$44 -> 0 | D26: ='02_Historical_IS_BS_CF'!$F$44 -> 0 | E26: ='02_Historical_IS_BS_CF'!$F$44 -> 0 | F26: ='02_Historical_IS_BS_CF'!$F$44 -> 0
A27: Other liabilities | B27: ='02_Historical_IS_BS_CF'!$F$45 -> 1310 | C27: ='02_Historical_IS_BS_CF'!$F$45 -> 1310 | D27: ='02_Historical_IS_BS_CF'!$F$45 -> 1310 | E27: ='02_Historical_IS_BS_CF'!$F$45 -> 1310 | F27: ='02_Historical_IS_BS_CF'!$F$45 -> 1310
A28: Total liabilities | B28: =B24+B25+B26+B27 -> 358295.82 | C28: =C24+C25+C26+C27 -> 364411.69 | D28: =D24+D25+D26+D27 -> 371036.47 | E28: =E24+E25+E26+E27 -> 378105.6 | F28: =F24+F25+F26+F27 -> 385529.97
A29: Common Stock | B29: ='02_Historical_IS_BS_CF'!$F$47 -> 12 | C29: ='02_Historical_IS_BS_CF'!$F$47 -> 12 | D29: ='02_Historical_IS_BS_CF'!$F$47 -> 12 | E29: ='02_Historical_IS_BS_CF'!$F$47 -> 12 | F29: ='02_Historical_IS_BS_CF'!$F$47 -> 12
A30: Additional paid-in capital | B30: =('02_Historical_IS_BS_CF'!$F$48)+'05_Forecast_CF'!B9 -> 1086865.1 | C30: =B30+'05_Forecast_CF'!C9 -> 1120585.6 | D30: =C30+'05_Forecast_CF'!D9 -> 1155460.6 | E30: =D30+'05_Forecast_CF'!E9 -> 1190903.9 | F30: =E30+'05_Forecast_CF'!F9 -> 1226231.5
A31: Accumulated deficit | B31: ='02_Historical_IS_BS_CF'!F49+'03_Forecast_IS'!B14 -> -658568.83 | C31: =B31+'03_Forecast_IS'!C14 -> -601378.16 | D31: =C31+'03_Forecast_IS'!D14 -> -509280.94 | E31: =D31+'03_Forecast_IS'!E14 -> -378076.28 | F31: =E31+'03_Forecast_IS'!F14 -> -204369.93
A32: Accumulated other comprehensive income | B32: ='02_Historical_IS_BS_CF'!$F$50 -> -1481 | C32: ='02_Historical_IS_BS_CF'!$F$50 -> -1481 | D32: ='02_Historical_IS_BS_CF'!$F$50 -> -1481 | E32: ='02_Historical_IS_BS_CF'!$F$50 -> -1481 | F32: ='02_Historical_IS_BS_CF'!$F$50 -> -1481
A33: Total stockholders' equity | B33: =SUM(B29:B32) -> 426827.28 | C33: =SUM(C29:C32) -> 517738.44 | D33: =SUM(D29:D32) -> 644710.64 | E33: =SUM(E29:E32) -> 811358.63 | F33: =SUM(F29:F32) -> 1020392.6
A34: Total liabilities and stockholders' equity | B34: =B28+B33 -> 785123.1 | C34: =C28+C33 -> 882150.12 | D34: =D28+D33 -> 1015747.1 | E34: =E28+E33 -> 1189464.2 | F34: =F28+F33 -> 1405922.5
A36: GOLDEN TIE: Assets = Liab + Equity | B36: =B15-B34 -> 0 | C36: =C15-C34 -> 0 | D36: =D15-D34 -> 0 | E36: =E15-E34 -> 0 | F36: =F15-F34 -> 0

Sheet 05_Forecast_CF
A1: Forecast Cash Flow Statement (FY2026 - FY2030, $ in thousands)
A3: Scenario: | B3: ='00_Control_Panel'!C4 -> Best
A6: Line Item | B6: 2026 | C6: =B6+1 -> 2027 | D6: =C6+1 -> 2028 | E6: =D6+1 -> 2029 | F6: =E6+1 -> 2030
A7: Net income (loss) | B7: ='03_Forecast_IS'!B14 -> 27011.174 | C7: ='03_Forecast_IS'!C14 -> 57190.668 | D7: ='03_Forecast_IS'!D14 -> 92097.221 | E7: ='03_Forecast_IS'!E14 -> 131204.66 | F7: ='03_Forecast_IS'!F14 -> 173706.34
A8: Depreciation and amortization | B8: ='06_Supporting_Schedules'!B16 -> 56150.682 | C8: ='06_Supporting_Schedules'!C16 -> 63440.244 | D8: ='06_Supporting_Schedules'!D16 -> 71041.642 | E8: ='06_Supporting_Schedules'!E16 -> 78843.306 | F8: ='06_Supporting_Schedules'!F16 -> 86713.17
A9: Stock-based compensation | B9: ='03_Forecast_IS'!B6*'01_Assumptions'!B33 -> 32086.104 | C9: ='03_Forecast_IS'!C6*'01_Assumptions'!C33 -> 33720.49 | D9: ='03_Forecast_IS'!D6*'01_Assumptions'!D33 -> 34874.988 | E9: ='03_Forecast_IS'!E6*'01_Assumptions'!E33 -> 35443.321 | F9: ='03_Forecast_IS'!F6*'01_Assumptions'!F33 -> 35327.588
A10: Change in accounts receivable | B10: =-('04_Forecast_BS'!B8-'02_Historical_IS_BS_CF'!F29) -> -11.517534 | C10: =-('04_Forecast_BS'!C8-'04_Forecast_BS'!B8) -> -461.51245 | D10: =-('04_Forecast_BS'!D8-'04_Forecast_BS'!C8) -> -488.5439 | E10: =-('04_Forecast_BS'!E8-'04_Forecast_BS'!D8) -> -509.58887 | F10: =-('04_Forecast_BS'!F8-'04_Forecast_BS'!E8) -> -523.1779
A11: Change in inventory | B11: =-('04_Forecast_BS'!B9-'02_Historical_IS_BS_CF'!F30) -> -2463.3749 | C11: =-('04_Forecast_BS'!C9-'04_Forecast_BS'!B9) -> -1800.7227 | D11: =-('04_Forecast_BS'!D9-'04_Forecast_BS'!C9) -> -1050.3694 | E11: =-('04_Forecast_BS'!E9-'04_Forecast_BS'!D9) -> -172.694 | F11: =-('04_Forecast_BS'!F9-'04_Forecast_BS'!E9) -> 813.30383
A12: Change in accounts payable | B12: ='04_Forecast_BS'!B19-'02_Historical_IS_BS_CF'!F37 -> 5106.8223 | C12: ='04_Forecast_BS'!C19-'04_Forecast_BS'!B19 -> 6115.8642 | D12: ='04_Forecast_BS'!D19-'04_Forecast_BS'!C19 -> 6624.7805 | E12: ='04_Forecast_BS'!E19-'04_Forecast_BS'!D19 -> 7069.13 | F12: ='04_Forecast_BS'!F19-'04_Forecast_BS'!E19 -> 7424.3701
A13: Net cash provided by operating activities | B13: =SUM(B7:B12) -> 117879.89 | C13: =SUM(C7:C12) -> 158205.03 | D13: =SUM(D7:D12) -> 203099.72 | E13: =SUM(E7:E12) -> 251878.14 | F13: =SUM(F7:F12) -> 303461.6
A14: Capital expenditures | B14: =-'06_Supporting_Schedules'!B15 -> -75201.806 | C14: =-'06_Supporting_Schedules'!C15 -> -84301.225 | D14: =-'06_Supporting_Schedules'!D15 -> -93645.801 | E14: =-'06_Supporting_Schedules'!E15 -> -103074.96 | F14: =-'06_Supporting_Schedules'!F15 -> -112405.96
A15: Net cash used in investing activities | B15: =B14 -> -75201.806 | C15: =C14 -> -84301.225 | D15: =D14 -> -93645.801 | E15: =E14 -> -103074.96 | F15: =F14 -> -112405.96
A16: Net cash provided by (used in) financing activities | B16: 0 | C16: 0 | D16: 0 | E16: 0 | F16: 0 | H16: No new financing modeled - WRBY carries no debt in the historical data
A17: Net increase (decrease) in cash | B17: =B13+B15+B16 -> 42678.084 | C17: =C13+C15+C16 -> 73903.805 | D17: =D13+D15+D16 -> 109453.92 | E17: =E13+E15+E16 -> 148803.17 | F17: =F13+F15+F16 -> 191055.64
A18: Cash, beginning of year | B18: ='02_Historical_IS_BS_CF'!F28 -> 286358 | C18: =B20 -> 329036.08 | D18: =C20 -> 402939.89 | E18: =D20 -> 512393.81 | F18: =E20 -> 661196.98
A20: Cash, end of year | B20: =B17+B18 -> 329036.08 | C20: =C17+C18 -> 402939.89 | D20: =D17+D18 -> 512393.81 | E20: =E17+E18 -> 661196.98 | F20: =F17+F18 -> 852252.61

Sheet 06_Supporting_Schedules
A1: Supporting Schedules (FY2026–FY2030, $ in thousands)
A3: Scenario: | B3: ='00_Control_Panel'!C4 -> Best
A5: Working Capital Schedule
A6: Line Item | B6: 2026 | C6: =B6+1 -> 2027 | D6: =C6+1 -> 2028 | E6: =D6+1 -> 2029 | F6: =E6+1 -> 2030
A7: Accounts receivable, net | B7: ='03_Forecast_IS'!B6/365 * '01_Assumptions'!B28 -> 3296.5175 | C7: ='03_Forecast_IS'!C6/365 * '01_Assumptions'!C28 -> 3758.03 | D7: ='03_Forecast_IS'!D6/365 * '01_Assumptions'!D28 -> 4246.5739 | E7: ='03_Forecast_IS'!E6/365 * '01_Assumptions'!E28 -> 4756.1628 | F7: ='03_Forecast_IS'!F6/365 * '01_Assumptions'!F28 -> 5279.3407
A8: Inventory | B8: ='03_Forecast_IS'!B7/365 * '01_Assumptions'!B29 -> 46975.375 | C8: ='03_Forecast_IS'!C7/365 * '01_Assumptions'!C29 -> 48776.098 | D8: ='03_Forecast_IS'!D7/365 * '01_Assumptions'!D29 -> 49826.467 | E8: ='03_Forecast_IS'!E7/365 * '01_Assumptions'!E29 -> 49999.161 | F8: ='03_Forecast_IS'!F7/365 * '01_Assumptions'!F29 -> 49185.857
A9: Accounts payable | B9: ='03_Forecast_IS'!B7/365 * '01_Assumptions'!B30 -> 37085.822 | C9: ='03_Forecast_IS'!C7/365 * '01_Assumptions'!C30 -> 43201.686 | D9: ='03_Forecast_IS'!D7/365 * '01_Assumptions'!D30 -> 49826.467 | E9: ='03_Forecast_IS'!E7/365 * '01_Assumptions'!E30 -> 56895.597 | F9: ='03_Forecast_IS'!F7/365 * '01_Assumptions'!F30 -> 64319.967
A12: PP&E Roll-Forward
A13: Line Item | B13: 2026 | C13: =B13+1 -> 2027 | D13: =C13+1 -> 2028 | E13: =D13+1 -> 2029 | F13: =E13+1 -> 2030
A14: Beginning PP&E, net | B14: ='02_Historical_IS_BS_CF'!F33 -> 187448 | C14: =B17 -> 206499.12 | D14: =C17 -> 227360.11 | E14: =D17 -> 249964.26 | F14: =E17 -> 274195.92
A15: Capital expenditures (capex) | B15: ='01_Assumptions'!B31*'03_Forecast_IS'!B6 -> 75201.806 | C15: ='01_Assumptions'!C31*'03_Forecast_IS'!C6 -> 84301.225 | D15: ='01_Assumptions'!D31*'03_Forecast_IS'!D6 -> 93645.801 | E15: ='01_Assumptions'!E31*'03_Forecast_IS'!E6 -> 103074.96 | F15: ='01_Assumptions'!F31*'03_Forecast_IS'!F6 -> 112405.96
A16: Depreciation and amortization | B16: ='03_Forecast_IS'!B6*'01_Assumptions'!B32 -> 56150.682 | C16: ='03_Forecast_IS'!C6*'01_Assumptions'!C32 -> 63440.244 | D16: ='03_Forecast_IS'!D6*'01_Assumptions'!D32 -> 71041.642 | E16: ='03_Forecast_IS'!E6*'01_Assumptions'!E32 -> 78843.306 | F16: ='03_Forecast_IS'!F6*'01_Assumptions'!F32 -> 86713.17
A17: Ending PP&E, net | B17: =B14+B15-B16 -> 206499.12 | C17: =C14+C15-C16 -> 227360.11 | D17: =D14+D15-D16 -> 249964.26 | E17: =E14+E15-E16 -> 274195.92 | F17: =F14+F15-F16 -> 299888.71

Sheet 07_Validation
A1: Model Validation Dashboard
A2: All checks should read TRUE / 0. Any FALSE or nonzero value indicates a broken link or formula error.
A4: Scenario: | B4: ='00_Control_Panel'!C4 -> Best
A6: Check | B6: 2026 | C6: =B6+1 -> 2027 | D6: =C6+1 -> 2028 | E6: =D6+1 -> 2029 | F6: =E6+1 -> 2030
A7: Balance Sheet balances | B7: ='04_Forecast_BS'!B15-'04_Forecast_BS'!B34 -> 0 | C7: ='04_Forecast_BS'!C15-'04_Forecast_BS'!C34 -> 0 | D7: ='04_Forecast_BS'!D15-'04_Forecast_BS'!D34 -> 0 | E7: ='04_Forecast_BS'!E15-'04_Forecast_BS'!E34 -> 0 | F7: ='04_Forecast_BS'!F15-'04_Forecast_BS'!F34 -> 0
A8: Cash Flow ties to Balance Sheet cash | B8: ='05_Forecast_CF'!B20-'04_Forecast_BS'!B7 -> 0 | C8: ='05_Forecast_CF'!C20-'04_Forecast_BS'!C7 -> 0 | D8: ='05_Forecast_CF'!D20-'04_Forecast_BS'!D7 -> 0 | E8: ='05_Forecast_CF'!E20-'04_Forecast_BS'!E7 -> 0 | F8: ='05_Forecast_CF'!F20-'04_Forecast_BS'!F7 -> 0
B9: 2021 | C9: =B9+1 -> 2022 | D9: =C9+1 -> 2023 | E9: =D9+1 -> 2024 | F9: =E9+1 -> 2025
A10: Historical Balance Sheet ties | B10: ='02_Historical_IS_BS_CF'!B36-'02_Historical_IS_BS_CF'!B52 -> 11 | C10: ='02_Historical_IS_BS_CF'!C36-'02_Historical_IS_BS_CF'!C52 -> 0 | D10: ='02_Historical_IS_BS_CF'!D36-'02_Historical_IS_BS_CF'!D52 -> 0 | E10: ='02_Historical_IS_BS_CF'!E36-'02_Historical_IS_BS_CF'!E52 -> 0 | F10: ='02_Historical_IS_BS_CF'!F36-'02_Historical_IS_BS_CF'!F52 -> 0
A11: Historical Cash Flow ties to Balance Sheet cash | B11: ='02_Historical_IS_BS_CF'!B95-'02_Historical_IS_BS_CF'!B28 -> 0 | C11: ='02_Historical_IS_BS_CF'!C95-'02_Historical_IS_BS_CF'!C28 -> 0 | D11: ='02_Historical_IS_BS_CF'!D95-'02_Historical_IS_BS_CF'!D28 -> 0 | E11: ='02_Historical_IS_BS_CF'!E95-'02_Historical_IS_BS_CF'!E28 -> 2 | F11: ='02_Historical_IS_BS_CF'!F95-'02_Historical_IS_BS_CF'!F28 -> 2
A12: Scenario validity check | B12: ='00_Control_Panel'!D4 -> ✓ Valid
A14: Overall model status: | B14: =IF(AND(ABS(B7)<=3,ABS(B8)<=3),"✓ Model integrity confirmed","⚠ Review required") -> ✓ Model integrity confirmed | C14: =IF(AND(ABS(C7)<=3,ABS(C8)<=3),"✓ Model integrity confirmed","⚠ Review required") -> ✓ Model integrity confirmed | D14: =IF(AND(ABS(D7)<=3,ABS(D8)<=3),"✓ Model integrity confirmed","⚠ Review required") -> ✓ Model integrity confirmed | E14: =IF(AND(ABS(E7)<=3,ABS(E8)<=3),"✓ Model integrity confirmed","⚠ Review required") -> ✓ Model integrity confirmed | F14: =IF(AND(ABS(F7)<=3,ABS(F8)<=3),"✓ Model integrity confirmed","⚠ Review required") -> ✓ Model integrity confirmed

Sheet 08_Scenario_Planner
A1: Scenario Comparison - Base vs. Best vs. Worst
A2: Independent of Control Panel toggle - shows all three scenarios at once.
A4: BASE CASE
A5: Revenue growth % | B5: =SUMIFS('10_Data_Sources'!$E$5:$E$154,'10_Data_Sources'!$A$5:$A$154,"revenue_growth_pct",'10_Data_Sources'!$C$5:$C$154,"base",'10_Data_Sources'!$D$5:$D$154,B$13) -> 0.13 | C5: =SUMIFS('10_Data_Sources'!$E$5:$E$154,'10_Data_Sources'!$A$5:$A$154,"revenue_growth_pct",'10_Data_Sources'!$C$5:$C$154,"base",'10_Data_Sources'!$D$5:$D$154,C$13) -> 0.115 | D5: =SUMIFS('10_Data_Sources'!$E$5:$E$154,'10_Data_Sources'!$A$5:$A$154,"revenue_growth_pct",'10_Data_Sources'!$C$5:$C$154,"base",'10_Data_Sources'!$D$5:$D$154,D$13) -> 0.1 | E5: =SUMIFS('10_Data_Sources'!$E$5:$E$154,'10_Data_Sources'!$A$5:$A$154,"revenue_growth_pct",'10_Data_Sources'!$C$5:$C$154,"base",'10_Data_Sources'!$D$5:$D$154,E$13) -> 0.085 | F5: =SUMIFS('10_Data_Sources'!$E$5:$E$154,'10_Data_Sources'!$A$5:$A$154,"revenue_growth_pct",'10_Data_Sources'!$C$5:$C$154,"base",'10_Data_Sources'!$D$5:$D$154,F$13) -> 0.07
A6: Gross margin % | B6: =SUMIFS('10_Data_Sources'!$E$5:$E$154,'10_Data_Sources'!$A$5:$A$154,"gross_margin_pct",'10_Data_Sources'!$C$5:$C$154,"base",'10_Data_Sources'!$D$5:$D$154,B$13) -> 0.545 | C6: =SUMIFS('10_Data_Sources'!$E$5:$E$154,'10_Data_Sources'!$A$5:$A$154,"gross_margin_pct",'10_Data_Sources'!$C$5:$C$154,"base",'10_Data_Sources'!$D$5:$D$154,C$13) -> 0.54625 | D6: =SUMIFS('10_Data_Sources'!$E$5:$E$154,'10_Data_Sources'!$A$5:$A$154,"gross_margin_pct",'10_Data_Sources'!$C$5:$C$154,"base",'10_Data_Sources'!$D$5:$D$154,D$13) -> 0.5475 | E6: =SUMIFS('10_Data_Sources'!$E$5:$E$154,'10_Data_Sources'!$A$5:$A$154,"gross_margin_pct",'10_Data_Sources'!$C$5:$C$154,"base",'10_Data_Sources'!$D$5:$D$154,E$13) -> 0.54875 | F6: =SUMIFS('10_Data_Sources'!$E$5:$E$154,'10_Data_Sources'!$A$5:$A$154,"gross_margin_pct",'10_Data_Sources'!$C$5:$C$154,"base",'10_Data_Sources'!$D$5:$D$154,F$13) -> 0.55
A7: SG&A % of revenue | B7: =SUMIFS('10_Data_Sources'!$E$5:$E$154,'10_Data_Sources'!$A$5:$A$154,"sga_pct_revenue",'10_Data_Sources'!$C$5:$C$154,"base",'10_Data_Sources'!$D$5:$D$154,B$13) -> 0.535 | C7: =SUMIFS('10_Data_Sources'!$E$5:$E$154,'10_Data_Sources'!$A$5:$A$154,"sga_pct_revenue",'10_Data_Sources'!$C$5:$C$154,"base",'10_Data_Sources'!$D$5:$D$154,C$13) -> 0.52125 | D7: =SUMIFS('10_Data_Sources'!$E$5:$E$154,'10_Data_Sources'!$A$5:$A$154,"sga_pct_revenue",'10_Data_Sources'!$C$5:$C$154,"base",'10_Data_Sources'!$D$5:$D$154,D$13) -> 0.5075 | E7: =SUMIFS('10_Data_Sources'!$E$5:$E$154,'10_Data_Sources'!$A$5:$A$154,"sga_pct_revenue",'10_Data_Sources'!$C$5:$C$154,"base",'10_Data_Sources'!$D$5:$D$154,E$13) -> 0.49375 | F7: =SUMIFS('10_Data_Sources'!$E$5:$E$154,'10_Data_Sources'!$A$5:$A$154,"sga_pct_revenue",'10_Data_Sources'!$C$5:$C$154,"base",'10_Data_Sources'!$D$5:$D$154,F$13) -> 0.48
A8: Effective tax rate % | B8: =SUMIFS('10_Data_Sources'!$E$5:$E$154,'10_Data_Sources'!$A$5:$A$154,"effective_tax_rate_pct",'10_Data_Sources'!$C$5:$C$154,"base",'10_Data_Sources'!$D$5:$D$154,B$13) -> 0.08 | C8: =SUMIFS('10_Data_Sources'!$E$5:$E$154,'10_Data_Sources'!$A$5:$A$154,"effective_tax_rate_pct",'10_Data_Sources'!$C$5:$C$154,"base",'10_Data_Sources'!$D$5:$D$154,C$13) -> 0.12 | D8: =SUMIFS('10_Data_Sources'!$E$5:$E$154,'10_Data_Sources'!$A$5:$A$154,"effective_tax_rate_pct",'10_Data_Sources'!$C$5:$C$154,"base",'10_Data_Sources'!$D$5:$D$154,D$13) -> 0.16 | E8: =SUMIFS('10_Data_Sources'!$E$5:$E$154,'10_Data_Sources'!$A$5:$A$154,"effective_tax_rate_pct",'10_Data_Sources'!$C$5:$C$154,"base",'10_Data_Sources'!$D$5:$D$154,E$13) -> 0.2 | F8: =SUMIFS('10_Data_Sources'!$E$5:$E$154,'10_Data_Sources'!$A$5:$A$154,"effective_tax_rate_pct",'10_Data_Sources'!$C$5:$C$154,"base",'10_Data_Sources'!$D$5:$D$154,F$13) -> 0.24
B13: 2026 | C13: =B13+1 -> 2027 | D13: =C13+1 -> 2028 | E13: =D13+1 -> 2029 | F13: =E13+1 -> 2030
A14: Net revenue | B14: ='02_Historical_IS_BS_CF'!$F$5*(1+B5) -> 985252.65 | C14: =B14*(1+C5) -> 1098556.7 | D14: =C14*(1+D5) -> 1208412.4 | E14: =D14*(1+E5) -> 1311127.4 | F14: =E14*(1+F5) -> 1402906.3
A15: Cost of goods sold | B15: =B14*(1-B6) -> 448289.96 | C15: =C14*(1-C6) -> 498470.1 | D15: =D14*(1-D6) -> 546806.6 | E15: =E14*(1-E6) -> 591646.25 | F15: =F14*(1-F6) -> 631307.86
A16: Gross profit | B16: =B14-B15 -> 536962.69 | C16: =C14-C15 -> 600086.6 | D16: =D14-D15 -> 661605.78 | E16: =E14-E15 -> 719481.18 | F16: =F14-F15 -> 771598.49
A17: SG&A | B17: =B14*B7 -> 527110.17 | C17: =C14*C7 -> 572622.68 | D17: =D14*D7 -> 613269.28 | E17: =E14*E7 -> 647369.17 | F17: =F14*F7 -> 673395.05
A18: Operating income (loss) | B18: =B16-B17 -> 9852.5265 | C18: =C16-C17 -> 27463.918 | D18: =D16-D17 -> 48336.495 | E18: =E16-E17 -> 72112.008 | F18: =F16-F17 -> 98203.444
A19: Interest and other income (loss), net | B19: ='02_Historical_IS_BS_CF'!$F$10 -> 8379 | C19: ='02_Historical_IS_BS_CF'!$F$10 -> 8379 | D19: ='02_Historical_IS_BS_CF'!$F$10 -> 8379 | E19: ='02_Historical_IS_BS_CF'!$F$10 -> 8379 | F19: ='02_Historical_IS_BS_CF'!$F$10 -> 8379
A20: Income before taxes | B20: =B18+B19 -> 18231.526 | C20: =C18+C19 -> 35842.918 | D20: =D18+D19 -> 56715.495 | E20: =E18+E19 -> 80491.008 | F20: =F18+F19 -> 106582.44
A21: Net income (loss) | B21: =IF(B20<=0,B20,B20-(B20*B8)) -> 16773.004 | C21: =IF(C20<=0,C20,C20-(C20*C8)) -> 31541.768 | D21: =IF(D20<=0,D20,D20-(D20*D8)) -> 47641.016 | E21: =IF(E20<=0,E20,E20-(E20*E8)) -> 64392.807 | F21: =IF(F20<=0,F20,F20-(F20*F8)) -> 81002.658
A24: BEST CASE
A25: Revenue growth % | B25: =SUMIFS('10_Data_Sources'!$E$5:$E$154,'10_Data_Sources'!$A$5:$A$154,"revenue_growth_pct",'10_Data_Sources'!$C$5:$C$154,"best",'10_Data_Sources'!$D$5:$D$154,B$33) -> 0.15 | C25: =SUMIFS('10_Data_Sources'!$E$5:$E$154,'10_Data_Sources'!$A$5:$A$154,"revenue_growth_pct",'10_Data_Sources'!$C$5:$C$154,"best",'10_Data_Sources'!$D$5:$D$154,C$33) -> 0.14 | D25: =SUMIFS('10_Data_Sources'!$E$5:$E$154,'10_Data_Sources'!$A$5:$A$154,"revenue_growth_pct",'10_Data_Sources'!$C$5:$C$154,"best",'10_Data_Sources'!$D$5:$D$154,D$33) -> 0.13 | E25: =SUMIFS('10_Data_Sources'!$E$5:$E$154,'10_Data_Sources'!$A$5:$A$154,"revenue_growth_pct",'10_Data_Sources'!$C$5:$C$154,"best",'10_Data_Sources'!$D$5:$D$154,E$33) -> 0.12 | F25: =SUMIFS('10_Data_Sources'!$E$5:$E$154,'10_Data_Sources'!$A$5:$A$154,"revenue_growth_pct",'10_Data_Sources'!$C$5:$C$154,"best",'10_Data_Sources'!$D$5:$D$154,F$33) -> 0.11
A26: Gross margin % | B26: =SUMIFS('10_Data_Sources'!$E$5:$E$154,'10_Data_Sources'!$A$5:$A$154,"gross_margin_pct",'10_Data_Sources'!$C$5:$C$154,"best",'10_Data_Sources'!$D$5:$D$154,B$33) -> 0.55 | C26: =SUMIFS('10_Data_Sources'!$E$5:$E$154,'10_Data_Sources'!$A$5:$A$154,"gross_margin_pct",'10_Data_Sources'!$C$5:$C$154,"best",'10_Data_Sources'!$D$5:$D$154,C$33) -> 0.555 | D26: =SUMIFS('10_Data_Sources'!$E$5:$E$154,'10_Data_Sources'!$A$5:$A$154,"gross_margin_pct",'10_Data_Sources'!$C$5:$C$154,"best",'10_Data_Sources'!$D$5:$D$154,D$33) -> 0.56 | E26: =SUMIFS('10_Data_Sources'!$E$5:$E$154,'10_Data_Sources'!$A$5:$A$154,"gross_margin_pct",'10_Data_Sources'!$C$5:$C$154,"best",'10_Data_Sources'!$D$5:$D$154,E$33) -> 0.565 | F26: =SUMIFS('10_Data_Sources'!$E$5:$E$154,'10_Data_Sources'!$A$5:$A$154,"gross_margin_pct",'10_Data_Sources'!$C$5:$C$154,"best",'10_Data_Sources'!$D$5:$D$154,F$33) -> 0.57
A27: SG&A % of revenue | B27: =SUMIFS('10_Data_Sources'!$E$5:$E$154,'10_Data_Sources'!$A$5:$A$154,"sga_pct_revenue",'10_Data_Sources'!$C$5:$C$154,"best",'10_Data_Sources'!$D$5:$D$154,B$33) -> 0.53 | C27: =SUMIFS('10_Data_Sources'!$E$5:$E$154,'10_Data_Sources'!$A$5:$A$154,"sga_pct_revenue",'10_Data_Sources'!$C$5:$C$154,"best",'10_Data_Sources'!$D$5:$D$154,C$33) -> 0.5075 | D27: =SUMIFS('10_Data_Sources'!$E$5:$E$154,'10_Data_Sources'!$A$5:$A$154,"sga_pct_revenue",'10_Data_Sources'!$C$5:$C$154,"best",'10_Data_Sources'!$D$5:$D$154,D$33) -> 0.485 | E27: =SUMIFS('10_Data_Sources'!$E$5:$E$154,'10_Data_Sources'!$A$5:$A$154,"sga_pct_revenue",'10_Data_Sources'!$C$5:$C$154,"best",'10_Data_Sources'!$D$5:$D$154,E$33) -> 0.4625 | F27: =SUMIFS('10_Data_Sources'!$E$5:$E$154,'10_Data_Sources'!$A$5:$A$154,"sga_pct_revenue",'10_Data_Sources'!$C$5:$C$154,"best",'10_Data_Sources'!$D$5:$D$154,F$33) -> 0.44
A28: Effective tax rate % | B28: =SUMIFS('10_Data_Sources'!$E$5:$E$154,'10_Data_Sources'!$A$5:$A$154,"effective_tax_rate_pct",'10_Data_Sources'!$C$5:$C$154,"best",'10_Data_Sources'!$D$5:$D$154,B$33) -> 0.05 | C28: =SUMIFS('10_Data_Sources'!$E$5:$E$154,'10_Data_Sources'!$A$5:$A$154,"effective_tax_rate_pct",'10_Data_Sources'!$C$5:$C$154,"best",'10_Data_Sources'!$D$5:$D$154,C$33) -> 0.0875 | D28: =SUMIFS('10_Data_Sources'!$E$5:$E$154,'10_Data_Sources'!$A$5:$A$154,"effective_tax_rate_pct",'10_Data_Sources'!$C$5:$C$154,"best",'10_Data_Sources'!$D$5:$D$154,D$33) -> 0.125 | E28: =SUMIFS('10_Data_Sources'!$E$5:$E$154,'10_Data_Sources'!$A$5:$A$154,"effective_tax_rate_pct",'10_Data_Sources'!$C$5:$C$154,"best",'10_Data_Sources'!$D$5:$D$154,E$33) -> 0.1625 | F28: =SUMIFS('10_Data_Sources'!$E$5:$E$154,'10_Data_Sources'!$A$5:$A$154,"effective_tax_rate_pct",'10_Data_Sources'!$C$5:$C$154,"best",'10_Data_Sources'!$D$5:$D$154,F$33) -> 0.2
B33: 2026 | C33: =B33+1 -> 2027 | D33: =C33+1 -> 2028 | E33: =D33+1 -> 2029 | F33: =E33+1 -> 2030
A34: Net revenue | B34: ='02_Historical_IS_BS_CF'!$F$5*(1+B25) -> 1002690.7 | C34: =B34*(1+C25) -> 1143067.5 | D34: =C34*(1+D25) -> 1291666.2 | E34: =D34*(1+E25) -> 1446666.2 | F34: =E34*(1+F25) -> 1605799.4
A35: Cost of goods sold | B35: =B34*(1-B26) -> 451210.84 | C35: =C34*(1-C26) -> 508665.02 | D35: =D34*(1-D26) -> 568333.14 | E35: =E34*(1-E26) -> 629299.78 | F35: =F34*(1-F26) -> 690493.76
A36: Gross profit | B36: =B34-B35 -> 551479.91 | C36: =C34-C35 -> 634402.44 | D36: =D34-D35 -> 723333.09 | E36: =E34-E35 -> 817366.39 | F36: =F34-F35 -> 915305.69
A37: SG&A | B37: =B34*B27 -> 531426.1 | C37: =C34*C27 -> 580106.73 | D37: =D34*D27 -> 626458.12 | E37: =E34*E27 -> 669083.1 | F37: =F34*F27 -> 706551.76
A38: Operating income (loss) | B38: =B36-B37 -> 20053.815 | C38: =C36-C37 -> 54295.704 | D38: =D36-D37 -> 96874.967 | E38: =E36-E37 -> 148283.28 | F38: =F36-F37 -> 208753.93
A39: Interest and other income (loss), net | B39: ='02_Historical_IS_BS_CF'!$F$10 -> 8379 | C39: ='02_Historical_IS_BS_CF'!$F$10 -> 8379 | D39: ='02_Historical_IS_BS_CF'!$F$10 -> 8379 | E39: ='02_Historical_IS_BS_CF'!$F$10 -> 8379 | F39: ='02_Historical_IS_BS_CF'!$F$10 -> 8379
A40: Income before taxes | B40: =B38+B39 -> 28432.815 | C40: =C38+C39 -> 62674.704 | D40: =D38+D39 -> 105253.97 | E40: =E38+E39 -> 156662.28 | F40: =F38+F39 -> 217132.93
A41: Net income (loss) | B41: =IF(B40<=0,B40,B40-(B40*B28)) -> 27011.174 | C41: =IF(C40<=0,C40,C40-(C40*C28)) -> 57190.668 | D41: =IF(D40<=0,D40,D40-(D40*D28)) -> 92097.221 | E41: =IF(E40<=0,E40,E40-(E40*E28)) -> 131204.66 | F41: =IF(F40<=0,F40,F40-(F40*F28)) -> 173706.34
A44: WORST CASE
A45: Revenue growth % | B45: =SUMIFS('10_Data_Sources'!$E$5:$E$154,'10_Data_Sources'!$A$5:$A$154,"revenue_growth_pct",'10_Data_Sources'!$C$5:$C$154,"worst",'10_Data_Sources'!$D$5:$D$154,B$53) -> 0.08 | C45: =SUMIFS('10_Data_Sources'!$E$5:$E$154,'10_Data_Sources'!$A$5:$A$154,"revenue_growth_pct",'10_Data_Sources'!$C$5:$C$154,"worst",'10_Data_Sources'!$D$5:$D$154,C$53) -> 0.0675 | D45: =SUMIFS('10_Data_Sources'!$E$5:$E$154,'10_Data_Sources'!$A$5:$A$154,"revenue_growth_pct",'10_Data_Sources'!$C$5:$C$154,"worst",'10_Data_Sources'!$D$5:$D$154,D$53) -> 0.055 | E45: =SUMIFS('10_Data_Sources'!$E$5:$E$154,'10_Data_Sources'!$A$5:$A$154,"revenue_growth_pct",'10_Data_Sources'!$C$5:$C$154,"worst",'10_Data_Sources'!$D$5:$D$154,E$53) -> 0.0425 | F45: =SUMIFS('10_Data_Sources'!$E$5:$E$154,'10_Data_Sources'!$A$5:$A$154,"revenue_growth_pct",'10_Data_Sources'!$C$5:$C$154,"worst",'10_Data_Sources'!$D$5:$D$154,F$53) -> 0.03
A46: Gross margin % | B46: =SUMIFS('10_Data_Sources'!$E$5:$E$154,'10_Data_Sources'!$A$5:$A$154,"gross_margin_pct",'10_Data_Sources'!$C$5:$C$154,"worst",'10_Data_Sources'!$D$5:$D$154,B$53) -> 0.535 | C46: =SUMIFS('10_Data_Sources'!$E$5:$E$154,'10_Data_Sources'!$A$5:$A$154,"gross_margin_pct",'10_Data_Sources'!$C$5:$C$154,"worst",'10_Data_Sources'!$D$5:$D$154,C$53) -> 0.52875 | D46: =SUMIFS('10_Data_Sources'!$E$5:$E$154,'10_Data_Sources'!$A$5:$A$154,"gross_margin_pct",'10_Data_Sources'!$C$5:$C$154,"worst",'10_Data_Sources'!$D$5:$D$154,D$53) -> 0.5225 | E46: =SUMIFS('10_Data_Sources'!$E$5:$E$154,'10_Data_Sources'!$A$5:$A$154,"gross_margin_pct",'10_Data_Sources'!$C$5:$C$154,"worst",'10_Data_Sources'!$D$5:$D$154,E$53) -> 0.51625 | F46: =SUMIFS('10_Data_Sources'!$E$5:$E$154,'10_Data_Sources'!$A$5:$A$154,"gross_margin_pct",'10_Data_Sources'!$C$5:$C$154,"worst",'10_Data_Sources'!$D$5:$D$154,F$53) -> 0.51
A47: SG&A % of revenue | B47: =SUMIFS('10_Data_Sources'!$E$5:$E$154,'10_Data_Sources'!$A$5:$A$154,"sga_pct_revenue",'10_Data_Sources'!$C$5:$C$154,"worst",'10_Data_Sources'!$D$5:$D$154,B$53) -> 0.545 | C47: =SUMIFS('10_Data_Sources'!$E$5:$E$154,'10_Data_Sources'!$A$5:$A$154,"sga_pct_revenue",'10_Data_Sources'!$C$5:$C$154,"worst",'10_Data_Sources'!$D$5:$D$154,C$53) -> 0.545 | D47: =SUMIFS('10_Data_Sources'!$E$5:$E$154,'10_Data_Sources'!$A$5:$A$154,"sga_pct_revenue",'10_Data_Sources'!$C$5:$C$154,"worst",'10_Data_Sources'!$D$5:$D$154,D$53) -> 0.545 | E47: =SUMIFS('10_Data_Sources'!$E$5:$E$154,'10_Data_Sources'!$A$5:$A$154,"sga_pct_revenue",'10_Data_Sources'!$C$5:$C$154,"worst",'10_Data_Sources'!$D$5:$D$154,E$53) -> 0.545 | F47: =SUMIFS('10_Data_Sources'!$E$5:$E$154,'10_Data_Sources'!$A$5:$A$154,"sga_pct_revenue",'10_Data_Sources'!$C$5:$C$154,"worst",'10_Data_Sources'!$D$5:$D$154,F$53) -> 0.545
A48: Effective tax rate % | B48: =SUMIFS('10_Data_Sources'!$E$5:$E$154,'10_Data_Sources'!$A$5:$A$154,"effective_tax_rate_pct",'10_Data_Sources'!$C$5:$C$154,"worst",'10_Data_Sources'!$D$5:$D$154,B$53) -> 0.12 | C48: =SUMIFS('10_Data_Sources'!$E$5:$E$154,'10_Data_Sources'!$A$5:$A$154,"effective_tax_rate_pct",'10_Data_Sources'!$C$5:$C$154,"worst",'10_Data_Sources'!$D$5:$D$154,C$53) -> 0.1575 | D48: =SUMIFS('10_Data_Sources'!$E$5:$E$154,'10_Data_Sources'!$A$5:$A$154,"effective_tax_rate_pct",'10_Data_Sources'!$C$5:$C$154,"worst",'10_Data_Sources'!$D$5:$D$154,D$53) -> 0.195 | E48: =SUMIFS('10_Data_Sources'!$E$5:$E$154,'10_Data_Sources'!$A$5:$A$154,"effective_tax_rate_pct",'10_Data_Sources'!$C$5:$C$154,"worst",'10_Data_Sources'!$D$5:$D$154,E$53) -> 0.2325 | F48: =SUMIFS('10_Data_Sources'!$E$5:$E$154,'10_Data_Sources'!$A$5:$A$154,"effective_tax_rate_pct",'10_Data_Sources'!$C$5:$C$154,"worst",'10_Data_Sources'!$D$5:$D$154,F$53) -> 0.27
B53: 2026 | C53: =B53+1 -> 2027 | D53: =C53+1 -> 2028 | E53: =D53+1 -> 2029 | F53: =E53+1 -> 2030
A54: Net revenue | B54: ='02_Historical_IS_BS_CF'!$F$5*(1+B45) -> 941657.4 | C54: =B54*(1+C45) -> 1005219.3 | D54: =C54*(1+D45) -> 1060506.3 | E54: =D54*(1+E45) -> 1105577.9 | F54: =E54*(1+F45) -> 1138745.2
A55: Cost of goods sold | B55: =B54*(1-B46) -> 437870.69 | C55: =C54*(1-C46) -> 473709.58 | D55: =D54*(1-D46) -> 506391.77 | E55: =E54*(1-E46) -> 534823.29 | F55: =F54*(1-F46) -> 557985.14
A56: Gross profit | B56: =B54-B55 -> 503786.71 | C56: =C54-C55 -> 531509.69 | D56: =D54-D55 -> 554114.56 | E56: =E54-E55 -> 570754.57 | F56: =F54-F55 -> 580760.05
A57: SG&A | B57: =B54*B47 -> 513203.28 | C57: =C54*C47 -> 547844.5 | D57: =D54*D47 -> 577975.95 | E57: =E54*E47 -> 602539.93 | F57: =F54*F47 -> 620616.13
A58: Operating income (loss) | B58: =B56-B57 -> -9416.574 | C58: =C56-C57 -> -16334.813 | D58: =D56-D57 -> -23861.393 | E58: =E56-E57 -> -31785.363 | F58: =F56-F57 -> -39856.082
A59: Interest and other income (loss), net | B59: ='02_Historical_IS_BS_CF'!$F$10 -> 8379 | C59: ='02_Historical_IS_BS_CF'!$F$10 -> 8379 | D59: ='02_Historical_IS_BS_CF'!$F$10 -> 8379 | E59: ='02_Historical_IS_BS_CF'!$F$10 -> 8379 | F59: ='02_Historical_IS_BS_CF'!$F$10 -> 8379
A60: Income before taxes | B60: =B58+B59 -> -1037.574 | C60: =C58+C59 -> -7955.8132 | D60: =D58+D59 -> -15482.393 | E60: =E58+E59 -> -23406.363 | F60: =F58+F59 -> -31477.082
A61: Net income (loss) | B61: =IF(B60<=0,B60,B60-(B60*B48)) -> -1037.574 | C61: =IF(C60<=0,C60,C60-(C60*C48)) -> -7955.8132 | D61: =IF(D60<=0,D60,D60-(D60*D48)) -> -15482.393 | E61: =IF(E60<=0,E60,E60-(E60*E48)) -> -23406.363 | F61: =IF(F60<=0,F60,F60-(F60*F48)) -> -31477.082
A64: 2030 Scenario Comparison
A65: Metric | B65: Base | C65: Best | D65: Worst
A66: Net revenue | B66: =F14 -> 1402906.3 | C66: =F34 -> 1605799.4 | D66: =F54 -> 1138745.2
A67: Net income (loss) | B67: =F21 -> 81002.658 | C67: =F41 -> 173706.34 | D67: =F61 -> -31477.082
A68: Net margin % | B68: =B67/B66 -> 0.057739177 | C68: =C67/C66 -> 0.10817437 | D68: =D67/D66 -> -0.027641901

Sheet 09_Dashboard
A1: Warby Parker (WRBY) - 3-Statement Model Dashboard
A2: FY2026–FY2030 Forecast | Scenario: | D2: ='00_Control_Panel'!C4 -> Best
A4: Key Metrics
A5: Metric | B5: 2026 | C5: 2030 | D5: 5-Yr Growth
A6: Net revenue | B6: ='03_Forecast_IS'!B6 -> 1002690.7 | C6: ='03_Forecast_IS'!F6 -> 1605799.4 | D6: =C6/B6-1 -> 0.60149024
A7: Gross profit | B7: ='03_Forecast_IS'!B8 -> 551479.91 | C7: ='03_Forecast_IS'!F8 -> 915305.69 | D7: =C7/B7-1 -> 0.65972625
A8: Operating income (loss) | B8: ='03_Forecast_IS'!B10 -> 20053.815 | C8: ='03_Forecast_IS'!F10 -> 208753.93 | D8: =C8/B8-1 -> 9.4096866
A9: Net income (loss) | B9: ='03_Forecast_IS'!B14 -> 27011.174 | C9: ='03_Forecast_IS'!F14 -> 173706.34 | D9: =C9/B9-1 -> 5.4309067
B11: 2026 | C11: =B11+1 -> 2027 | D11: =C11+1 -> 2028 | E11: =D11+1 -> 2029 | F11: =E11+1 -> 2030
A12: Gross margin % | B12: ='03_Forecast_IS'!B8/'03_Forecast_IS'!B6 -> 0.55 | C12: ='03_Forecast_IS'!C8/'03_Forecast_IS'!C6 -> 0.555 | D12: ='03_Forecast_IS'!D8/'03_Forecast_IS'!D6 -> 0.56 | E12: ='03_Forecast_IS'!E8/'03_Forecast_IS'!E6 -> 0.565 | F12: ='03_Forecast_IS'!F8/'03_Forecast_IS'!F6 -> 0.57
A13: Operating margin % | B13: ='03_Forecast_IS'!B10/'03_Forecast_IS'!B6 -> 0.02 | C13: ='03_Forecast_IS'!C10/'03_Forecast_IS'!C6 -> 0.0475 | D13: ='03_Forecast_IS'!D10/'03_Forecast_IS'!D6 -> 0.075 | E13: ='03_Forecast_IS'!E10/'03_Forecast_IS'!E6 -> 0.1025 | F13: ='03_Forecast_IS'!F10/'03_Forecast_IS'!F6 -> 0.13
A14: Net margin % | B14: ='03_Forecast_IS'!B14/'03_Forecast_IS'!B6 -> 0.026938689 | C14: ='03_Forecast_IS'!C14/'03_Forecast_IS'!C6 -> 0.050032627 | D14: ='03_Forecast_IS'!D14/'03_Forecast_IS'!D6 -> 0.071301099 | E14: ='03_Forecast_IS'!E14/'03_Forecast_IS'!E6 -> 0.090694498 | F14: ='03_Forecast_IS'!F14/'03_Forecast_IS'!F6 -> 0.10817437
A17: Year | B17: 2026 | C17: =B17+1 -> 2027 | D17: =C17+1 -> 2028 | E17: =D17+1 -> 2029 | F17: =E17+1 -> 2030
A18: Net revenue | B18: ='03_Forecast_IS'!B6 -> 1002690.7 | C18: ='03_Forecast_IS'!C6 -> 1143067.5 | D18: ='03_Forecast_IS'!D6 -> 1291666.2 | E18: ='03_Forecast_IS'!E6 -> 1446666.2 | F18: ='03_Forecast_IS'!F6 -> 1605799.4
A19: Net income (loss) | B19: ='03_Forecast_IS'!B14 -> 27011.174 | C19: ='03_Forecast_IS'!C14 -> 57190.668 | D19: ='03_Forecast_IS'!D14 -> 92097.221 | E19: ='03_Forecast_IS'!E14 -> 131204.66 | F19: ='03_Forecast_IS'!F14 -> 173706.34
A35: 2030 Scenario Snapshot
A36: Metric | B36: Base | C36: Best | D36: Worst
A37: Net revenue | B37: ='08_Scenario_Planner'!F14 -> 1402906.3 | C37: ='08_Scenario_Planner'!F34 -> 1605799.4 | D37: ='08_Scenario_Planner'!F54 -> 1138745.2
A38: Net income (loss) | B38: ='08_Scenario_Planner'!F21 -> 81002.658 | C38: ='08_Scenario_Planner'!F41 -> 173706.34 | D38: ='08_Scenario_Planner'!F61 -> -31477.082

Sheet 10_Data_Sources
A1: DATA SOURCES - RAW IMPORTS
A3: Scenario Assumptions
A4: driver | B4: driver_label | C4: scenario | D4: year | E4: value | F4: rationale
A5: revenue_growth_pct | B5: Revenue growth % | C5: base | D5: 2026 | E5: 0.13 | F5: Starts near the FY24-25 average growth rate (~14.1%), decelerating to 7% by year 5 - typical maturation curve for a scaling DTC retailer, consistent with WRBY's own deceleration from 15.2% (FY24) to 13.0% (FY25).
A6: revenue_growth_pct | B6: Revenue growth % | C6: base | D6: 2027 | E6: 0.115 | F6: Starts near the FY24-25 average growth rate (~14.1%), decelerating to 7% by year 5 - typical maturation curve for a scaling DTC retailer, consistent with WRBY's own deceleration from 15.2% (FY24) to 13.0% (FY25).
A7: revenue_growth_pct | B7: Revenue growth % | C7: base | D7: 2028 | E7: 0.1 | F7: Starts near the FY24-25 average growth rate (~14.1%), decelerating to 7% by year 5 - typical maturation curve for a scaling DTC retailer, consistent with WRBY's own deceleration from 15.2% (FY24) to 13.0% (FY25).
A8: revenue_growth_pct | B8: Revenue growth % | C8: base | D8: 2029 | E8: 0.085 | F8: Starts near the FY24-25 average growth rate (~14.1%), decelerating to 7% by year 5 - typical maturation curve for a scaling DTC retailer, consistent with WRBY's own deceleration from 15.2% (FY24) to 13.0% (FY25).
A9: revenue_growth_pct | B9: Revenue growth % | C9: base | D9: 2030 | E9: 0.07 | F9: Starts near the FY24-25 average growth rate (~14.1%), decelerating to 7% by year 5 - typical maturation curve for a scaling DTC retailer, consistent with WRBY's own deceleration from 15.2% (FY24) to 13.0% (FY25).
A10: revenue_growth_pct | B10: Revenue growth % | C10: best | D10: 2026 | E10: 0.15 | F10: Holds near FY24's peak growth rate (15.2%) and decelerates more slowly - new store productivity and category expansion (contacts, exams) sustain growth longer.
A11: revenue_growth_pct | B11: Revenue growth % | C11: best | D11: 2027 | E11: 0.14 | F11: Holds near FY24's peak growth rate (15.2%) and decelerates more slowly - new store productivity and category expansion (contacts, exams) sustain growth longer.
A12: revenue_growth_pct | B12: Revenue growth % | C12: best | D12: 2028 | E12: 0.13 | F12: Holds near FY24's peak growth rate (15.2%) and decelerates more slowly - new store productivity and category expansion (contacts, exams) sustain growth longer.
A13: revenue_growth_pct | B13: Revenue growth % | C13: best | D13: 2029 | E13: 0.12 | F13: Holds near FY24's peak growth rate (15.2%) and decelerates more slowly - new store productivity and category expansion (contacts, exams) sustain growth longer.
A14: revenue_growth_pct | B14: Revenue growth % | C14: best | D14: 2030 | E14: 0.11 | F14: Holds near FY24's peak growth rate (15.2%) and decelerates more slowly - new store productivity and category expansion (contacts, exams) sustain growth longer.
A15: revenue_growth_pct | B15: Revenue growth % | C15: worst | D15: 2026 | E15: 0.08 | F15: Growth roughly halves from the FY25 rate immediately - reflects competitive/macro pressure on discretionary eyewear spend, decelerating to GDP-like growth by year 5.
A16: revenue_growth_pct | B16: Revenue growth % | C16: worst | D16: 2027 | E16: 0.0675 | F16: Growth roughly halves from the FY25 rate immediately - reflects competitive/macro pressure on discretionary eyewear spend, decelerating to GDP-like growth by year 5.
... A154: sbc_pct_revenue | B154: Stock-based comp % of revenue | C154: worst | D154: 2030 | E154: 0.045 | F154: New equity grants increase to retain talent amid competitive hiring pressure.
A157: Historical Ratios
A158: driver | B158: 2021 | C158: 2022 | D158: 2023 | E158: 2024 | F158: 2025
A159: revenue_growth_pct | C159: 0.10598042 | D159: 0.11979863 | E159: 0.15162034 | F159: 0.13041364
A160: gross_margin_pct | B160: 0.5875558 | C160: 0.57023099 | D160: 0.54530171 | E160: 0.5533848 | F160: 0.53971362
A161: cogs_pct_revenue | B161: 0.4124442 | C161: 0.42976901 | D161: 0.45469829 | E161: 0.4466152 | F161: 0.46028638
A162: sga_pct_revenue | B162: 0.85320212 | C162: 0.75615437 | D162: 0.65279613 | E162: 0.59242463 | F162: 0.54583355
A163: operating_margin_pct | B163: -0.26564632 | C163: -0.18592337 | D163: -0.10749442 | E163: -0.039039822 | F163: -0.0061199328
A164: net_margin_pct | B164: -0.26677429 | C164: -0.18456911 | D164: -0.094356976 | E164: -0.026435373 | F164: 0.0018820858
A165: effective_tax_rate_pct | F165: 0.46072954
A166: dso_days | B166: 0.6695291 | C166: 0.87571391 | D166: 0.96949676 | E166: 0.92182831 | F166: 1.3751785
A167: dio_days | B167: 93.430928 | C167: 97.761214 | D167: 74.589004 | E167: 55.462928 | F167: 40.482999
A168: dpo_days | B168: 50.548758 | C168: 29.52233 | D168: 26.914077 | E168: 24.919909 | F168: 29.084423
A169: capex_pct_revenue | B169: 0.089706323 | C169: 0.10061828 | D169: 0.080134077 | E169: 0.083016666 | F169: 0.076898286
A170: da_pct_revenue | B170: 0.04043654 | C170: 0.053274303 | D170: 0.057563474 | E170: 0.059463384 | F170: 0.057666833
A171: sbc_pct_revenue | B171: 0.19812943 | C171: 0.16390241 | D171: 0.10527424 | E171: 0.061316064 | F171: 0.03960982
